{
  "leo acho zuppa": {
    "mail": "leonardo.acho@upc.edu",
    "office": null
  },
  "david agis cherta": {
    "mail": "david.agis@upc.edu",
    "office": null
  },
  "francesc d'asis lluis aguilo gost": {
    "mail": "francesc.aguilo@upc.edu",
    "office": "Edifici C3 Despatx 110"
  },
  "maria alberich carrami\u00f1ana": {
    "mail": "maria.alberich@upc.edu",
    "office": null
  },
  "edwin santiago alferez baquero": {
    "mail": "santiago.alferez@upc.edu",
    "office": null
  },
  "maria teresa alonso alonso": {
    "mail": "maria.teresa.alonso@upc.edu",
    "office": "Edifici C3C  C. Esteve Terradas, 5 08860 Castelldefels Spain</Td></Tr><Tr> <Td Valign=\"Top\" Class=\"Subtitol2\">Tel&Egrave;Fon</Td><Td Class=\"Blau2\">934054436</Td></Tr><Tr> <Td Valign=\"Top\" Class=\"Subtitol2\">Producci\\Xf3 Cient\\Xedfica: </Td><Td Class=\"Blau2\"><A Href=\"Http://Futur.Upc.Edu/Mariateresaalonsoalonso\">Futur.Upc.Edu/Mariateresaalonsoalonso</A></Td></Tr><Tr><Td Colspan=\"2\">&Nbsp;</Td> </Tr><Tr Class=\"Titol_Contingut\"><Td Colspan=\"2\"> <B>Pas: Personal D\\'Administraci\\Xf3 I Serveis</B></Td></Tr><Tr> <Td Valign=\"Top\" Class=\"Subtitol2\">Adre&Ccedil;A De Correu </Td><Td Class=\"Blau2\"><Span Class=\"Mail\">Maria.Teresa.Alonso<Img Src=\"Img/Arrobag.Gif\" Align=\"Top\"/>Upc.Edu</Span></Td></Tr><Tr> <Td Valign=\"Top\" Class=\"Subtitol2\">Adre&Ccedil;A </Td><Td Class=\"Blau2\"><A Href=\"Dadesue.Jsp?Id=749\">Matem\\Xe0Tiques</A> Edifici C3 Despatx 211"
  },
  "montserrat alsina aubach": {
    "mail": "montserrat.alsina@upc.edu",
    "office": null
  },
  "josep alvarez montaner": {
    "mail": "josep.alvarez@upc.edu",
    "office": null
  },
  "rafel amer ramon": {
    "mail": "rafel.amer@upc.edu",
    "office": null
  },
  "jaume amoros torrent": {
    "mail": "jaume.amoros@upc.edu",
    "office": null
  },
  "josefina antonijuan rull": {
    "mail": "josefina.antonijuan@upc.edu",
    "office": null
  },
  "josep maria aroca farrerons": {
    "mail": "josep.m.aroca@upc.edu",
    "office": "Edifici C3 Despatx:  217"
  },
  "inmaculada baldoma barraca": {
    "mail": "immaculada.baldoma@upc.edu",
    "office": null
  },
  "simeon michael ball": {
    "mail": "simeon.michael.ball@upc.edu",
    "office": null
  },
  "miguel angel barja ya\u00f1ez": {
    "mail": "miguel.angel.barja@upc.edu",
    "office": null
  },
  "daniel barrera salazar": {
    "mail": "daniel.barrera.salazar@upc.edu",
    "office": "Edifici Omega Planta 4 Despatx 419"
  },
  "lali barriere figueroa": {
    "mail": "lali.barriere@upc.edu",
    "office": null
  },
  "carles batlle arnau": {
    "mail": "carles.batlle@upc.edu",
    "office": null
  },
  "monica blanco abellan": {
    "mail": "monica.blanco@upc.edu",
    "office": null
  },
  "guillem blanco fernandez": {
    "mail": "guillem.blanco@upc.edu",
    "office": null
  },
  "carles bonet reves": {
    "mail": "carles.bonet@upc.edu",
    "office": null
  },
  "santiago boza rocho": {
    "mail": "santiago.boza@upc.edu",
    "office": null
  },
  "maria montserrat bruguera padro": {
    "mail": "m.montserrat.bruguera@upc.edu",
    "office": null
  },
  "pablo buenestado caballero": {
    "mail": "pablo.buenestado@upc.edu",
    "office": null
  },
  "pep burillo puig": {
    "mail": "pep.burillo@upc.edu",
    "office": "Edifici C3 Despatx 105"
  },
  "xavier cabre vilagut": {
    "mail": "xavier.cabre@upc.edu",
    "office": null
  },
  "maria del pilar cano vila": {
    "mail": "m.pilar.cano@upc.edu",
    "office": "Edifici Omega 4 411"
  },
  "angeles carmona mejias": {
    "mail": "angeles.carmona@upc.edu",
    "office": null
  },
  "francesc carreras escobar": {
    "mail": "francesc.carreras@upc.edu",
    "office": null
  },
  "marta casanellas rius": {
    "mail": "marta.casanellas@upc.edu",
    "office": null
  },
  "jose manuel casta\u00f1ar ca\u00f1as": {
    "mail": "jose.manuel.castanar@upc.edu",
    "office": null
  },
  "merce claverol aguas": {
    "mail": "merce.claverol@upc.edu",
    "office": null
  },
  "jose clotet juan": {
    "mail": "josep.clotet@upc.edu",
    "office": null
  },
  "francesc de paula comellas padro": {
    "mail": "francesc.comellas@upc.edu",
    "office": null
  },
  "albert compta creus": {
    "mail": "albert.compta@upc.edu",
    "office": null
  },
  "neus consul porras": {
    "mail": "neus.consul@upc.edu",
    "office": null
  },
  "josep m. cors iglesias": {
    "mail": "josep.m.cors@upc.edu",
    "office": null
  },
  "matteo cozzi": {
    "mail": "matteo.cozzi@upc.edu",
    "office": null
  },
  "rafael cubarsi morera": {
    "mail": "rafael.cubarsi@upc.edu",
    "office": "Edifici C3 "
  },
  "amadeu delshams i valdes": {
    "mail": "amadeu.delshams@upc.edu",
    "office": null
  },
  "anna de mier vinue": {
    "mail": "anna.de.mier@upc.edu",
    "office": "Edifici Omega Despatx 437 - Planta4\\Xaa"
  },
  "roisin mary dempsey bradell": {
    "mail": "roisin.braddell@upc.edu",
    "office": null
  },
  "david diaz rodriguez": {
    "mail": "david.diaz-rodriguez@upc.edu",
    "office": "Edifici C3 "
  },
  "margarita domenech blazquez": {
    "mail": "margarita.domenech@upc.edu",
    "office": null
  },
  "jose francisco dominguez sevilla": {
    "mail": "jose.dominguez@upc.edu",
    "office": null
  },
  "josep elgueta monto": {
    "mail": "josep.elgueta@upc.edu",
    "office": "Edifici Omega Despatx 410"
  },
  "raimon elgueta monto": {
    "mail": "raimon.elgueta@upc.edu",
    "office": "Edifici Omega Despatx 337"
  },
  "andres marcos encinas bachiller": {
    "mail": "andres.marcos.encinas@upc.edu",
    "office": null
  },
  "miquel escudero royo": {
    "mail": "miquel.escudero@upc.edu",
    "office": "Edifici C3 Despatx:  205C"
  },
  "margarida espona dones": {
    "mail": "margarida.espona@upc.edu",
    "office": null
  },
  "josep fabrega canudas": {
    "mail": "josep.fabrega@upc.edu",
    "office": "Edifici C3 Despatx 112"
  },
  "jaume fabregat fillet": {
    "mail": "jaime.fabregat@upc.edu",
    "office": null
  },
  "rafel farre cirera": {
    "mail": "rafel.farre@upc.edu",
    "office": "Edifici Omega Planta 3 Despatx 335"
  },
  "yury fedorov kuzmin": {
    "mail": "yuri.fedorov@upc.edu",
    "office": null
  },
  "julio fernandez gonzalez": {
    "mail": "julio.fernandez.g@upc.edu",
    "office": null
  },
  "jesus fernandez sanchez": {
    "mail": "jesus.fernandez.sanchez@upc.edu",
    "office": null
  },
  "josep ferrer llop": {
    "mail": "josep.ferrer@upc.edu",
    "office": null
  },
  "miguel angel fiol mora": {
    "mail": "miguel.angel.fiol@upc.edu",
    "office": "Edifici C3 Despatx:  109"
  },
  "francesc fite naya": {
    "mail": "francesc.fite@upc.edu",
    "office": "Edifici Omega Despatx 409"
  },
  "santiago forcada plaza": {
    "mail": "santiago.forcada@upc.edu",
    "office": null
  },
  "jaume franch bullich": {
    "mail": "jaume.franch@upc.edu",
    "office": "Edifici C3 Despatx: 203"
  },
  "josep freixas bosch": {
    "mail": "josep.freixas@upc.edu",
    "office": null
  },
  "silvia gago alvarez": {
    "mail": "silvia.gago@upc.edu",
    "office": null
  },
  "imma galvez carrillo": {
    "mail": "m.immaculada.galvez@upc.edu",
    "office": null
  },
  "yamila garcia martinez": {
    "mail": "yamila.garcia@upc.edu",
    "office": null
  },
  "maria isabel garcia planas": {
    "mail": "maria.isabel.garcia@upc.edu",
    "office": null
  },
  "alberto garcia rigo": {
    "mail": "alberto.garcia.rigo@upc.edu",
    "office": "Edifici C3 Planta 1 Despatx 104"
  },
  "francesca gatti": {
    "mail": "francesca.gatti@upc.edu",
    "office": "Edifici Omega Planta 3"
  },
  "josep gibergans baguena": {
    "mail": "jose.gibergans@upc.edu",
    "office": null
  },
  "daniel gil mu\u00f1oz": {
    "mail": "daniel.gil.munoz@upc.edu",
    "office": "Edifici Omega "
  },
  "jose miguel gimenez pradales": {
    "mail": "jose.miguel.gimenez@upc.edu",
    "office": null
  },
  "marta ginovart gisbert": {
    "mail": "marta.ginovart@upc.edu",
    "office": null
  },
  "joan vicen\u00e7 gomez urgelles": {
    "mail": "joan.vicenc.gomez@upc.edu",
    "office": null
  },
  "rodrigo gon\u00e7alves schaefer": {
    "mail": "rodrigo.schaefer@upc.edu",
    "office": null
  },
  "guillermo gonzalez casado": {
    "mail": "guillermo.gonzalez@upc.edu",
    "office": "Edifici Omega Despaxt 418"
  },
  "maria isabel gonzalez perez": {
    "mail": "maria.isabel.gonzalez.perez@upc.edu",
    "office": "Edifici C6 "
  },
  "josep gonzalez rovira": {
    "mail": "josep.gonzalez@upc.edu",
    "office": null
  },
  "ignacio gracia rivas": {
    "mail": "ignacio.gracia@upc.edu",
    "office": "Edifici C3 Despatx:  304"
  },
  "xavier gracia sabate": {
    "mail": "xavier.gracia@upc.edu",
    "office": "Edifici C3 Despatx:  206"
  },
  "albert granados corsellas": {
    "mail": "albert.granados.corsellas@upc.edu",
    "office": null
  },
  "maria \u00e0ngela grau gotes": {
    "mail": "angela.grau@upc.edu",
    "office": "Edifici Omega Planta 4, Despatx 439"
  },
  "marcel guardia munarriz": {
    "mail": "marcel.guardia@upc.edu",
    "office": null
  },
  "jordi guardia rubies": {
    "mail": "jordi.guardia-rubies@upc.edu",
    "office": null
  },
  "antoni guillamon grabolosa": {
    "mail": "antoni.guillamon@upc.edu",
    "office": null
  },
  "pere gutierrez serres": {
    "mail": "pere.gutierrez@upc.edu",
    "office": null
  },
  "jaime haro cases": {
    "mail": "jaime.haro@upc.edu",
    "office": null
  },
  "maria isabel hernandez lopez": {
    "mail": "maria.isabel.hernandez.lopez@upc.edu",
    "office": "Edifici B6 "
  },
  "manuel hernandez pajares": {
    "mail": "manuel.hernandez@upc.edu",
    "office": "Edifici C3 Despatx 209"
  },
  "carmen hernando martin": {
    "mail": "carmen.hernando@upc.edu",
    "office": null
  },
  "javier herranz sotoca": {
    "mail": "javier.herranz@upc.edu",
    "office": null
  },
  "clemens huemer": {
    "mail": "clemens.huemer@upc.edu",
    "office": null
  },
  "gemma huguet casades": {
    "mail": "gemma.huguet@upc.edu",
    "office": null
  },
  "fay\u00e7al ikhouane": {
    "mail": "faycal.ikhouane@upc.edu",
    "office": null
  },
  "m. jose jimenez jimenez": {
    "mail": "maria.jose.jimenez@upc.edu",
    "office": null
  },
  "jorge jimenez urroz": {
    "mail": "jorge.urroz@upc.edu",
    "office": "Edifici C3 "
  },
  "tetiana klymchuk": {
    "mail": "tetiana.klymchuk@upc.edu",
    "office": null
  },
  "joan c. lario loyo": {
    "mail": "joan.carles.lario@upc.edu",
    "office": "Edifici Omega Planta 3 Despatx 336"
  },
  "jose tomas lazaro ochoa": {
    "mail": "jose.tomas.lazaro@upc.edu",
    "office": null
  },
  "fatima ezzahra lembarki el ammari": {
    "mail": "fatima.ezzahra.lembarki@upc.edu",
    "office": null
  },
  "mari carme leseduarte milan": {
    "mail": "mari.carme.leseduarte@upc.edu",
    "office": null
  },
  "anna llado sanchez": {
    "mail": "aina.llado@upc.edu",
    "office": "Edifici C3 Despatx 109"
  },
  "maria dolors llongueras arola": {
    "mail": "m.dolors.llongueras@upc.edu",
    "office": null
  },
  "pere lopez brosa": {
    "mail": "pere.lopez@upc.edu",
    "office": null
  },
  "susana clara lopez masip": {
    "mail": "susana.clara.lopez@upc.edu",
    "office": null
  },
  "jose antonio lubary martinez": {
    "mail": "jose.a.lubary@upc.edu",
    "office": "Edifici Omega Despatx 334"
  },
  "antonio maga\u00f1a nieto": {
    "mail": "antonio.magana@upc.edu",
    "office": null
  },
  "m. dolors magret planas": {
    "mail": "m.dolors.magret@upc.edu",
    "office": null
  },
  "victor ma\u00f1osa fernandez": {
    "mail": "victor.manosa@upc.edu",
    "office": null
  },
  "jaume marti farre": {
    "mail": "jaume.marti@upc.edu",
    "office": "Edifici Omega Planta 3 Despatx 333"
  },
  "pau martin de la torre": {
    "mail": "p.martin@upc.edu",
    "office": "Edifici C3 Despatx 216"
  },
  "sebastia martin mollevi": {
    "mail": "sebastia.martin@upc.edu",
    "office": "Edifici C3 Planta 2 Despatx 205B"
  },
  "fernando martinez saez": {
    "mail": "fernando.martinez@upc.edu",
    "office": "Edifici Omega Planta 3, Despatx 340"
  },
  "maria teresa martinez-seara alonso": {
    "mail": "tere.m-seara@upc.edu",
    "office": null
  },
  "josep joaquim masdemont soler": {
    "mail": "josep.masdemont@upc.edu",
    "office": null
  },
  "maria rosa massa esteve": {
    "mail": "m.rosa.massa@upc.edu",
    "office": null
  },
  "immaculada massana hugas": {
    "mail": "immaculada.massana@upc.edu",
    "office": null
  },
  "montserrat maureso sanchez": {
    "mail": "montserrat.maureso@upc.edu",
    "office": "Edifici Omega Planta 3, Despatx 332"
  },
  "eva miranda galceran": {
    "mail": "eva.miranda@upc.edu",
    "office": null
  },
  "margarida mitjana riera": {
    "mail": "margarida.mitjana@upc.edu",
    "office": null
  },
  "santiago molina blanco": {
    "mail": "santiago.molina@upc.edu",
    "office": "Edifici Omega Planta 3"
  },
  "m. antonia molina hernandez": {
    "mail": "m.antonia.molina@upc.edu",
    "office": null
  },
  "xavier molinero albareda": {
    "mail": "xavier.molinero@upc.edu",
    "office": null
  },
  "enrique pedro jaime monso burgues": {
    "mail": "enrique.monso@upc.edu",
    "office": null
  },
  "eulalia montoro lopez": {
    "mail": "maria.eulalia.montoro@upc.edu",
    "office": "Edifici B6 "
  },
  "merc\u00e8 mora gine": {
    "mail": "merce.mora@upc.edu",
    "office": "Edifici Omega Despatx 431"
  },
  "maria paz morillo bosch": {
    "mail": "paz.morillo@upc.edu",
    "office": "Edifici C3 "
  },
  "luis eduardo mujica delgado": {
    "mail": "luis.eduardo.mujica@upc.edu",
    "office": null
  },
  "miguel carlos mu\u00f1oz lecanda": {
    "mail": "miguel.carlos.munoz@upc.edu",
    "office": "Edifici C3 Despatx 106"
  },
  "xavier mu\u00f1oz lopez": {
    "mail": "xavier.munoz@upc.edu",
    "office": "Edifici C3 Despatx 111"
  },
  "jose javier mu\u00f1oz romero": {
    "mail": "j.munoz@upc.edu",
    "office": null
  },
  "timothy myers": {
    "mail": "timothy.myers@upc.edu",
    "office": null
  },
  "maria teresa navarro gonzalo": {
    "mail": "m.teresa.navarro@upc.edu",
    "office": null
  },
  "miquel noguera batlle": {
    "mail": "miquel.noguera@upc.edu",
    "office": null
  },
  "marc noy serrano": {
    "mail": "marc.noy@upc.edu",
    "office": "Edifici Omega Despatx 436"
  },
  "maria mercedes olle torner": {
    "mail": "merce.olle@upc.edu",
    "office": null
  },
  "josep maria olm miras": {
    "mail": "josep.olm@upc.edu",
    "office": null
  },
  "cedric oms": {
    "mail": "cedric.oms@upc.edu",
    "office": null
  },
  "dimitar ouzounov": {
    "mail": "dimitar.ouzounov@upc.edu",
    "office": "Edifici C3 209"
  },
  "juan ramon pacha andujar": {
    "mail": "juan.ramon.pacha@upc.edu",
    "office": null
  },
  "carles padro laimon": {
    "mail": "carles.padro@upc.edu",
    "office": "Edifici C3 Despatx:  213"
  },
  "francisco palacios qui\u00f1onero": {
    "mail": "francisco.palacios@upc.edu",
    "office": null
  },
  "chara pantazi": {
    "mail": "chara.pantazi@upc.edu",
    "office": null
  },
  "nuria pares marine": {
    "mail": "nuria.pares@upc.edu",
    "office": null
  },
  "pere pascual gainza": {
    "mail": "pere.pascual@upc.edu",
    "office": null
  },
  "ignacio manuel pelayo melero": {
    "mail": "ignacio.m.pelayo@upc.edu",
    "office": null
  },
  "marta pe\u00f1a carrera": {
    "mail": "marta.penya@upc.edu",
    "office": null
  },
  "alberto perez cervera": {
    "mail": "alberto.perez@upc.edu",
    "office": null
  },
  "sonia perez mansilla": {
    "mail": "sonia.perez-mansilla@upc.edu",
    "office": null
  },
  "maria jesus perez martin": {
    "mail": "maria.jesus.perez@upc.edu",
    "office": null
  },
  "julian pfeifle": {
    "mail": "julian.pfeifle@upc.edu",
    "office": "Edifici Omega Despatx 312, Planta 3"
  },
  "francesc planas vilanova": {
    "mail": "francesc.planas@upc.edu",
    "office": null
  },
  "bernat plans berenguer": {
    "mail": "bernat.plans@upc.edu",
    "office": null
  },
  "montserrat pons valles": {
    "mail": "montserrat.pons@upc.edu",
    "office": null
  },
  "francesc pozo montero": {
    "mail": "francesc.pozo@upc.edu",
    "office": null
  },
  "joana d'arc prat farran": {
    "mail": "joana.darc.prat@upc.edu",
    "office": null
  },
  "francesc prats duaygues": {
    "mail": "francesc.prats@upc.edu",
    "office": "Edifici Omega Despatx 341"
  },
  "maria albina puente del campo": {
    "mail": "m.albina.puente@upc.edu",
    "office": null
  },
  "francisco javier puerta coll": {
    "mail": "francisco.javier.puerta@upc.edu",
    "office": null
  },
  "anna puig montada": {
    "mail": "anna.puig@upc.edu",
    "office": null
  },
  "carles puig pla": {
    "mail": "carles.puig@upc.edu",
    "office": null
  },
  "joaquim puig sadurni": {
    "mail": "joaquim.puig@upc.edu",
    "office": null
  },
  "gisela pujol vazquez": {
    "mail": "gisela.pujol@upc.edu",
    "office": null
  },
  "jordi quer bosor": {
    "mail": "jordi.quer@upc.edu",
    "office": "Edifici Omega Despatx 438"
  },
  "ramon quintanilla de latorre": {
    "mail": "ramon.quintanilla@upc.edu",
    "office": null
  },
  "miquel rallo capdevila": {
    "mail": "miquel.rallo@upc.edu",
    "office": null
  },
  "jose matias ramirez moreno": {
    "mail": "jose.matias.ramirez@upc.edu",
    "office": null
  },
  "rodrigo ramirez pisco": {
    "mail": "rodrigo.ramirez.pisco@upc.edu",
    "office": null
  },
  "rafael ramirez ros": {
    "mail": "rafael.ramirez@upc.edu",
    "office": null
  },
  "antoni ras sabido": {
    "mail": "antoni.ras@upc.edu",
    "office": null
  },
  "anna rio doval": {
    "mail": "ana.rio@upc.edu",
    "office": "Edifici Omega Despatx 338"
  },
  "oscar rivero salgado": {
    "mail": "oscar.rivero@upc.edu",
    "office": "Edifici Omega Planta 2"
  },
  "jordi roca lacostena": {
    "mail": "jordi.roca.lacostena@upc.edu",
    "office": null
  },
  "antoni roca rosell": {
    "mail": "antoni.roca-rosell@upc.edu",
    "office": null
  },
  "jose rodellar benede": {
    "mail": "jose.rodellar@upc.edu",
    "office": null
  },
  "oscar rodriguez del rio": {
    "mail": "oscar.rodriguez@upc.edu",
    "office": null
  },
  "juan rodriguez jordana": {
    "mail": "juan.rodriguez@upc.edu",
    "office": null
  },
  "agusti roig marti": {
    "mail": "agustin.roig@upc.edu",
    "office": null
  },
  "narciso roman roy": {
    "mail": "narciso.roman@upc.edu",
    "office": "Edifici C3 Despatx:  205A"
  },
  "josep maria rossell garriga": {
    "mail": "josep.maria.rossell@upc.edu",
    "office": null
  },
  "victor rotger cerd\u00e0": {
    "mail": "victor.rotger@upc.edu",
    "office": "Edifici Omega Despatx 413"
  },
  "josep rubio massegu": {
    "mail": "josep.rubio@upc.edu",
    "office": null
  },
  "juan jose rue perna": {
    "mail": "juan.jose.rue@upc.edu",
    "office": null
  },
  "jose luis ruiz mu\u00f1oz": {
    "mail": "jose.luis.ruiz@upc.edu",
    "office": "Edifici Omega Despatx 425"
  },
  "magda ruiz ordo\u00f1ez": {
    "mail": "magda.ruiz@upc.edu",
    "office": null
  },
  "assumpta sabater pruna": {
    "mail": "assumpta.sabater-pruna@upc.edu",
    "office": null
  },
  "vera sacristan adinolfi": {
    "mail": "vera.sacristan@upc.edu",
    "office": "Edifici Omega Despatx 432"
  },
  "natalia sadovskaia nurimanova": {
    "mail": "natalia.sadovskaia@upc.edu",
    "office": "Edifici Omega Despatx: 440"
  },
  "german saez moreno": {
    "mail": "german.saez@upc.edu",
    "office": "Edifici C3 Despatx 216"
  },
  "vicen\u00e7 sales ingles": {
    "mail": "vicenc.sales@upc.edu",
    "office": null
  },
  "jordi saludes closa": {
    "mail": "jordi.saludes@upc.edu",
    "office": null
  },
  "m\u00f3nica sanchez soler": {
    "mail": "monica.sanchez@upc.edu",
    "office": "Edifici Omega Despatx 342"
  },
  "robert santos gutierrez": {
    "mail": "robert.santos@upc.edu",
    "office": null
  },
  "tomas sanz perela": {
    "mail": "tomas.sanz@upc.edu",
    "office": null
  },
  "jaime sanz subirana": {
    "mail": "jaume.sanz@upc.edu",
    "office": "Edifici C3 Despatx 213"
  },
  "carlos seara ojea": {
    "mail": "carlos.seara@upc.edu",
    "office": "Edifici Omega Planta 4, Despatx 424"
  },
  "oriol serra albo": {
    "mail": "oriol.serra@upc.edu",
    "office": "Edifici C3 Despatx:  112"
  },
  "carles serrat pie": {
    "mail": "carles.serrat@upc.edu",
    "office": null
  },
  "rodrigo ignacio silveira": {
    "mail": "rodrigo.silveira@upc.edu",
    "office": "Edifici Omega Planta 4 Despatx 422"
  },
  "ester simo mezquita": {
    "mail": "ester.simo@upc.edu",
    "office": null
  },
  "joan sola-morales rubio": {
    "mail": "jc.sola-morales@upc.edu",
    "office": null
  },
  "christoph spiegel": {
    "mail": "christoph.spiegel@upc.edu",
    "office": "Edifici Omega Planta 4"
  },
  "antonio susin sanchez": {
    "mail": "toni.susin@upc.edu",
    "office": null
  },
  "francesc ti\u00f1ena salva\u00f1a": {
    "mail": "francesc.tinena@upc.edu",
    "office": "Edifici Omega Despatx 429"
  },
  "joan trias pairo": {
    "mail": "joan.trias@upc.edu",
    "office": "Edifici Omega Despatx 433"
  },
  "enric trullols farreny": {
    "mail": "enric.trullols@upc.edu",
    "office": null
  },
  "marta valencia guitart": {
    "mail": "marta.valencia@upc.edu",
    "office": null
  },
  "luis valencia lopez": {
    "mail": "lluis.valencia@upc.edu",
    "office": "Edifici B6 "
  },
  "montse vela del olmo": {
    "mail": "montse.vela@upc.edu",
    "office": "Edifici Omega Despatx 430"
  },
  "robert velasquez barrio": {
    "mail": "robert.velasquez@upc.edu",
    "office": null
  },
  "enric ventura capell": {
    "mail": "enric.ventura@upc.edu",
    "office": null
  },
  "yolanda vidal segui": {
    "mail": "yolanda.vidal@upc.edu",
    "office": null
  },
  "francesc vilamajo capdevila": {
    "mail": "francesc.vilamajo@upc.edu",
    "office": null
  },
  "jordi villanueva castelltort": {
    "mail": "jordi.villanueva@upc.edu",
    "office": null
  },
  "jorge luis villar santos": {
    "mail": "jorge.villar@upc.edu",
    "office": "Edifici C3 Despatx:  219"
  },
  "sebasti\u00e0 xambo descamps": {
    "mail": "sebastia.xambo@upc.edu",
    "office": "Edifici Omega Planta 4 Despatx 428"
  },
  "neus ybern carballo": {
    "mail": "neus.ybern@upc.edu",
    "office": null
  },
  "maria luisa zaragoza monroig": {
    "mail": "marisa.zaragoza@upc.edu",
    "office": null
  }
}