{
  "469557458": {
    "name": "V\u00edctor",
    "language": "es",
    "access_token": "f0mqMIpb8OAM3YXYMvUnw47uLCH4OV62kCIS7LCiVto=",
    "refresh_token": "3EYpFDGhbB6b1xQgDy9KZOxxkuWTiRDnnbd9J6Re5KY=",
    "current_state": "0",
    "expire_time_end": {
      "day": 2,
      "month": 7,
      "year": 2018,
      "hour": 20,
      "minute": 10,
      "second": 12
    },
    "logged": true,
    "notifications": true
  },
  "312420157": {
    "name": "Joel",
    "refresh_token": "/xc//fH3W/ioEJo6Ai6d8jqbSdP0bb5o4rH+hRww/Eg=",
    "notifications": true,
    "current_state": "0",
    "expire_time_end": {
      "day": 2,
      "month": 7,
      "year": 2018,
      "hour": 20,
      "minute": 10,
      "second": 12
    },
    "language": "ca",
    "logged": true,
    "access_token": "thUI4c7nr1jwuY+t6nP+gCOQ3Ykqjk0TsHlN+4c6CkY="
  },
  "461088493": {
    "name": "Albert",
    "refresh_token": "9Jth3+68jL/PQYZwUcBu0p75FxgWA4KjwgC3DqLgd3s=",
    "notifications": true,
    "current_state": "0",
    "expire_time_end": {
      "day": 2,
      "month": 7,
      "year": 2018,
      "hour": 20,
      "minute": 10,
      "second": 12
    },
    "language": "ca",
    "logged": true,
    "access_token": "kj63fsZOw89ANGYlUJT5Vji0zjLgZ/A1VMudlduOL1Y="
  },
  "349611162": {
    "name": "Carla",
    "refresh_token": "BnL746ce6JwEOlEEI9zMcNrxv2/6Np3wPBIn7uXglFc=",
    "notifications": true,
    "current_state": "0",
    "expire_time_end": {
      "day": 2,
      "month": 7,
      "year": 2018,
      "hour": 20,
      "minute": 10,
      "second": 13
    },
    "language": "ca",
    "logged": true,
    "access_token": "d29DnFXZnsk6WueDHNk2VwGdnTUcqamnM3qsrOLNEsg="
  },
  "443306157": {
    "name": "Daniel",
    "language": "es",
    "access_token": "vodnokyMf29/xippEik2piHit2X4zMdDquhvkXEW/b8=",
    "refresh_token": "g7410clkW6aKaXA5iL2anem3pDvLW0UMf1Bp2og7Fxk=",
    "current_state": "0",
    "expire_time_end": {
      "day": 2,
      "month": 7,
      "year": 2018,
      "hour": 20,
      "minute": 10,
      "second": 13
    },
    "logged": true,
    "notifications": true
  },
  "473862645": {
    "name": "Lulzx",
    "language": "en",
    "access_token": null,
    "refresh_token": null,
    "current_state": "2",
    "expire_time_end": null,
    "logged": false,
    "notifications": false
  },
  "300145899": {
    "name": "Aitzol",
    "language": "en",
    "access_token": null,
    "refresh_token": null,
    "current_state": "0",
    "expire_time_end": null,
    "logged": false,
    "notifications": false
  }
}