{
  "rasa_nlu_data": {
    "regex_features": [],
    "entity_synonyms": [
      {
        "value": "correo",
        "synonyms": [
          "mail",
          "correo electr\u00f3nico",
          "email",
          "correo electronico"
        ]
      }
    ],
    "common_examples": [
      {
        "text": "cual es el correo de maria teresa abad soriano",
        "intent": "ask_teacher_mail",
        "entities": [
          {
            "start": 21,
            "end": 26,
            "value": "maria",
            "entity": "teacher_name"
          },
          {
            "start": 27,
            "end": 46,
            "value": "teresa abad soriano",
            "entity": "teacher_surname"
          }
        ]
      },
      {
        "text": "correo de maria teresa abad soriano",
        "intent": "ask_teacher_mail",
        "entities": [
          {
            "start": 10,
            "end": 15,
            "value": "maria",
            "entity": "teacher_name"
          },
          {
            "start": 16,
            "end": 35,
            "value": "teresa abad soriano",
            "entity": "teacher_surname"
          }
        ]
      },
      {
        "text": "cual es el correo de alicia maria ageno pulido",
        "intent": "ask_teacher_mail",
        "entities": [
          {
            "start": 21,
            "end": 27,
            "value": "alicia",
            "entity": "teacher_name"
          },
          {
            "start": 28,
            "end": 46,
            "value": "maria ageno pulido",
            "entity": "teacher_surname"
          }
        ]
      },
      {
        "text": "correo de alicia maria ageno pulido",
        "intent": "ask_teacher_mail",
        "entities": [
          {
            "start": 10,
            "end": 16,
            "value": "alicia",
            "entity": "teacher_name"
          },
          {
            "start": 17,
            "end": 35,
            "value": "maria ageno pulido",
            "entity": "teacher_surname"
          }
        ]
      },
      {
        "text": "cual es el correo de jesus alonso alonso",
        "intent": "ask_teacher_mail",
        "entities": [
          {
            "start": 21,
            "end": 26,
            "value": "jesus",
            "entity": "teacher_name"
          },
          {
            "start": 27,
            "end": 40,
            "value": "alonso alonso",
            "entity": "teacher_surname"
          }
        ]
      },
      {
        "text": "correo de jesus alonso alonso",
        "intent": "ask_teacher_mail",
        "entities": [
          {
            "start": 10,
            "end": 15,
            "value": "jesus",
            "entity": "teacher_name"
          },
          {
            "start": 16,
            "end": 29,
            "value": "alonso alonso",
            "entity": "teacher_surname"
          }
        ]
      },
      {
        "text": "cual es el correo de marcus aloysius bezem",
        "intent": "ask_teacher_mail",
        "entities": [
          {
            "start": 21,
            "end": 27,
            "value": "marcus",
            "entity": "teacher_name"
          },
          {
            "start": 28,
            "end": 42,
            "value": "aloysius bezem",
            "entity": "teacher_surname"
          }
        ]
      },
      {
        "text": "correo de marcus aloysius bezem",
        "intent": "ask_teacher_mail",
        "entities": [
          {
            "start": 10,
            "end": 16,
            "value": "marcus",
            "entity": "teacher_name"
          },
          {
            "start": 17,
            "end": 31,
            "value": "aloysius bezem",
            "entity": "teacher_surname"
          }
        ]
      },
      {
        "text": "cual es el correo de ren\u00c3\u00a9 alquezar mancho",
        "intent": "ask_teacher_mail",
        "entities": [
          {
            "start": 21,
            "end": 26,
            "value": "ren\u00c3\u00a9",
            "entity": "teacher_name"
          },
          {
            "start": 27,
            "end": 42,
            "value": "alquezar mancho",
            "entity": "teacher_surname"
          }
        ]
      },
      {
        "text": "correo de ren\u00c3\u00a9 alquezar mancho",
        "intent": "ask_teacher_mail",
        "entities": [
          {
            "start": 10,
            "end": 15,
            "value": "ren\u00c3\u00a9",
            "entity": "teacher_name"
          },
          {
            "start": 16,
            "end": 31,
            "value": "alquezar mancho",
            "entity": "teacher_surname"
          }
        ]
      },
      {
        "text": "cual es el correo de maria del carme alvarez faura",
        "intent": "ask_teacher_mail",
        "entities": [
          {
            "start": 21,
            "end": 26,
            "value": "maria",
            "entity": "teacher_name"
          },
          {
            "start": 27,
            "end": 50,
            "value": "del carme alvarez faura",
            "entity": "teacher_surname"
          }
        ]
      },
      {
        "text": "correo de maria del carme alvarez faura",
        "intent": "ask_teacher_mail",
        "entities": [
          {
            "start": 10,
            "end": 15,
            "value": "maria",
            "entity": "teacher_name"
          },
          {
            "start": 16,
            "end": 39,
            "value": "del carme alvarez faura",
            "entity": "teacher_surname"
          }
        ]
      },
      {
        "text": "cual es el correo de carlos andujar gran",
        "intent": "ask_teacher_mail",
        "entities": [
          {
            "start": 21,
            "end": 27,
            "value": "carlos",
            "entity": "teacher_name"
          },
          {
            "start": 28,
            "end": 40,
            "value": "andujar gran",
            "entity": "teacher_surname"
          }
        ]
      },
      {
        "text": "correo de carlos andujar gran",
        "intent": "ask_teacher_mail",
        "entities": [
          {
            "start": 10,
            "end": 16,
            "value": "carlos",
            "entity": "teacher_name"
          },
          {
            "start": 17,
            "end": 29,
            "value": "andujar gran",
            "entity": "teacher_surname"
          }
        ]
      },
      {
        "text": "cual es el correo de oscar argudo medrano",
        "intent": "ask_teacher_mail",
        "entities": [
          {
            "start": 21,
            "end": 26,
            "value": "oscar",
            "entity": "teacher_name"
          },
          {
            "start": 27,
            "end": 41,
            "value": "argudo medrano",
            "entity": "teacher_surname"
          }
        ]
      },
      {
        "text": "correo de oscar argudo medrano",
        "intent": "ask_teacher_mail",
        "entities": [
          {
            "start": 10,
            "end": 15,
            "value": "oscar",
            "entity": "teacher_name"
          },
          {
            "start": 16,
            "end": 30,
            "value": "argudo medrano",
            "entity": "teacher_surname"
          }
        ]
      },
      {
        "text": "cual es el correo de marta arias vicente",
        "intent": "ask_teacher_mail",
        "entities": [
          {
            "start": 21,
            "end": 26,
            "value": "marta",
            "entity": "teacher_name"
          },
          {
            "start": 27,
            "end": 40,
            "value": "arias vicente",
            "entity": "teacher_surname"
          }
        ]
      },
      {
        "text": "correo de marta arias vicente",
        "intent": "ask_teacher_mail",
        "entities": [
          {
            "start": 10,
            "end": 15,
            "value": "marta",
            "entity": "teacher_name"
          },
          {
            "start": 16,
            "end": 29,
            "value": "arias vicente",
            "entity": "teacher_surname"
          }
        ]
      },
      {
        "text": "cual es el correo de argimiro arratia quesada",
        "intent": "ask_teacher_mail",
        "entities": [
          {
            "start": 21,
            "end": 29,
            "value": "argimiro",
            "entity": "teacher_name"
          },
          {
            "start": 30,
            "end": 45,
            "value": "arratia quesada",
            "entity": "teacher_surname"
          }
        ]
      },
      {
        "text": "correo de argimiro arratia quesada",
        "intent": "ask_teacher_mail",
        "entities": [
          {
            "start": 10,
            "end": 18,
            "value": "argimiro",
            "entity": "teacher_name"
          },
          {
            "start": 19,
            "end": 34,
            "value": "arratia quesada",
            "entity": "teacher_surname"
          }
        ]
      },
      {
        "text": "cual es el correo de albert atserias peri",
        "intent": "ask_teacher_mail",
        "entities": [
          {
            "start": 21,
            "end": 27,
            "value": "albert",
            "entity": "teacher_name"
          },
          {
            "start": 28,
            "end": 41,
            "value": "atserias peri",
            "entity": "teacher_surname"
          }
        ]
      },
      {
        "text": "correo de albert atserias peri",
        "intent": "ask_teacher_mail",
        "entities": [
          {
            "start": 10,
            "end": 16,
            "value": "albert",
            "entity": "teacher_name"
          },
          {
            "start": 17,
            "end": 30,
            "value": "atserias peri",
            "entity": "teacher_surname"
          }
        ]
      },
      {
        "text": "cual es el correo de maria dolors ayala vallespi",
        "intent": "ask_teacher_mail",
        "entities": [
          {
            "start": 21,
            "end": 26,
            "value": "maria",
            "entity": "teacher_name"
          },
          {
            "start": 27,
            "end": 48,
            "value": "dolors ayala vallespi",
            "entity": "teacher_surname"
          }
        ]
      },
      {
        "text": "correo de maria dolors ayala vallespi",
        "intent": "ask_teacher_mail",
        "entities": [
          {
            "start": 10,
            "end": 15,
            "value": "maria",
            "entity": "teacher_name"
          },
          {
            "start": 16,
            "end": 37,
            "value": "dolors ayala vallespi",
            "entity": "teacher_surname"
          }
        ]
      },
      {
        "text": "cual es el correo de jaume baixeries juvilla",
        "intent": "ask_teacher_mail",
        "entities": [
          {
            "start": 21,
            "end": 26,
            "value": "jaume",
            "entity": "teacher_name"
          },
          {
            "start": 27,
            "end": 44,
            "value": "baixeries juvilla",
            "entity": "teacher_surname"
          }
        ]
      },
      {
        "text": "correo de jaume baixeries juvilla",
        "intent": "ask_teacher_mail",
        "entities": [
          {
            "start": 10,
            "end": 15,
            "value": "jaume",
            "entity": "teacher_name"
          },
          {
            "start": 16,
            "end": 33,
            "value": "baixeries juvilla",
            "entity": "teacher_surname"
          }
        ]
      },
      {
        "text": "cual es el correo de jose luis balcazar navarro",
        "intent": "ask_teacher_mail",
        "entities": [
          {
            "start": 21,
            "end": 25,
            "value": "jose",
            "entity": "teacher_name"
          },
          {
            "start": 26,
            "end": 47,
            "value": "luis balcazar navarro",
            "entity": "teacher_surname"
          }
        ]
      },
      {
        "text": "correo de jose luis balcazar navarro",
        "intent": "ask_teacher_mail",
        "entities": [
          {
            "start": 10,
            "end": 14,
            "value": "jose",
            "entity": "teacher_name"
          },
          {
            "start": 15,
            "end": 36,
            "value": "luis balcazar navarro",
            "entity": "teacher_surname"
          }
        ]
      },
      {
        "text": "cual es el correo de cristian barrue subirana",
        "intent": "ask_teacher_mail",
        "entities": [
          {
            "start": 21,
            "end": 29,
            "value": "cristian",
            "entity": "teacher_name"
          },
          {
            "start": 30,
            "end": 45,
            "value": "barrue subirana",
            "entity": "teacher_surname"
          }
        ]
      },
      {
        "text": "correo de cristian barrue subirana",
        "intent": "ask_teacher_mail",
        "entities": [
          {
            "start": 10,
            "end": 18,
            "value": "cristian",
            "entity": "teacher_name"
          },
          {
            "start": 19,
            "end": 34,
            "value": "barrue subirana",
            "entity": "teacher_surname"
          }
        ]
      },
      {
        "text": "cual es el correo de javier bejar alonso",
        "intent": "ask_teacher_mail",
        "entities": [
          {
            "start": 21,
            "end": 27,
            "value": "javier",
            "entity": "teacher_name"
          },
          {
            "start": 28,
            "end": 40,
            "value": "bejar alonso",
            "entity": "teacher_surname"
          }
        ]
      },
      {
        "text": "correo de javier bejar alonso",
        "intent": "ask_teacher_mail",
        "entities": [
          {
            "start": 10,
            "end": 16,
            "value": "javier",
            "entity": "teacher_name"
          },
          {
            "start": 17,
            "end": 29,
            "value": "bejar alonso",
            "entity": "teacher_surname"
          }
        ]
      },
      {
        "text": "cual es el correo de luis antonio belanche mu\u00c3\u00b1oz",
        "intent": "ask_teacher_mail",
        "entities": [
          {
            "start": 21,
            "end": 25,
            "value": "luis",
            "entity": "teacher_name"
          },
          {
            "start": 26,
            "end": 49,
            "value": "antonio belanche mu\u00c3\u00b1oz",
            "entity": "teacher_surname"
          }
        ]
      },
      {
        "text": "correo de luis antonio belanche mu\u00c3\u00b1oz",
        "intent": "ask_teacher_mail",
        "entities": [
          {
            "start": 10,
            "end": 14,
            "value": "luis",
            "entity": "teacher_name"
          },
          {
            "start": 15,
            "end": 38,
            "value": "antonio belanche mu\u00c3\u00b1oz",
            "entity": "teacher_surname"
          }
        ]
      },
      {
        "text": "cual es el correo de maria josep blesa aguilera",
        "intent": "ask_teacher_mail",
        "entities": [
          {
            "start": 21,
            "end": 26,
            "value": "maria",
            "entity": "teacher_name"
          },
          {
            "start": 27,
            "end": 47,
            "value": "josep blesa aguilera",
            "entity": "teacher_surname"
          }
        ]
      },
      {
        "text": "correo de maria josep blesa aguilera",
        "intent": "ask_teacher_mail",
        "entities": [
          {
            "start": 10,
            "end": 15,
            "value": "maria",
            "entity": "teacher_name"
          },
          {
            "start": 16,
            "end": 36,
            "value": "josep blesa aguilera",
            "entity": "teacher_surname"
          }
        ]
      },
      {
        "text": "cual es el correo de blum blum",
        "intent": "ask_teacher_mail",
        "entities": [
          {
            "start": 21,
            "end": 25,
            "value": "blum",
            "entity": "teacher_name"
          },
          {
            "start": 26,
            "end": 30,
            "value": "blum",
            "entity": "teacher_surname"
          }
        ]
      },
      {
        "text": "correo de blum blum",
        "intent": "ask_teacher_mail",
        "entities": [
          {
            "start": 10,
            "end": 14,
            "value": "blum",
            "entity": "teacher_name"
          },
          {
            "start": 15,
            "end": 19,
            "value": "blum",
            "entity": "teacher_surname"
          }
        ]
      },
      {
        "text": "cual es el correo de ilario bonacina",
        "intent": "ask_teacher_mail",
        "entities": [
          {
            "start": 21,
            "end": 27,
            "value": "ilario",
            "entity": "teacher_name"
          },
          {
            "start": 28,
            "end": 36,
            "value": "bonacina",
            "entity": "teacher_surname"
          }
        ]
      },
      {
        "text": "correo de ilario bonacina",
        "intent": "ask_teacher_mail",
        "entities": [
          {
            "start": 10,
            "end": 16,
            "value": "ilario",
            "entity": "teacher_name"
          },
          {
            "start": 17,
            "end": 25,
            "value": "bonacina",
            "entity": "teacher_surname"
          }
        ]
      },
      {
        "text": "cual es el despacho de maria teresa abad soriano",
        "intent": "ask_teacher_desk",
        "entities": [
          {
            "start": 23,
            "end": 28,
            "value": "maria",
            "entity": "teacher_name"
          },
          {
            "start": 29,
            "end": 48,
            "value": "teresa abad soriano",
            "entity": "teacher_surname"
          }
        ]
      },
      {
        "text": "despacho de maria teresa abad soriano",
        "intent": "ask_teacher_desk",
        "entities": [
          {
            "start": 12,
            "end": 17,
            "value": "maria",
            "entity": "teacher_name"
          },
          {
            "start": 18,
            "end": 37,
            "value": "teresa abad soriano",
            "entity": "teacher_surname"
          }
        ]
      },
      {
        "text": "dime el despacho de maria teresa abad soriano",
        "intent": "ask_teacher_desk",
        "entities": [
          {
            "start": 20,
            "end": 25,
            "value": "maria",
            "entity": "teacher_name"
          },
          {
            "start": 26,
            "end": 45,
            "value": "teresa abad soriano",
            "entity": "teacher_surname"
          }
        ]
      },
      {
        "text": "cual es el despacho de alicia maria ageno pulido",
        "intent": "ask_teacher_desk",
        "entities": [
          {
            "start": 23,
            "end": 29,
            "value": "alicia",
            "entity": "teacher_name"
          },
          {
            "start": 30,
            "end": 48,
            "value": "maria ageno pulido",
            "entity": "teacher_surname"
          }
        ]
      },
      {
        "text": "despacho de alicia maria ageno pulido",
        "intent": "ask_teacher_desk",
        "entities": [
          {
            "start": 12,
            "end": 18,
            "value": "alicia",
            "entity": "teacher_name"
          },
          {
            "start": 19,
            "end": 37,
            "value": "maria ageno pulido",
            "entity": "teacher_surname"
          }
        ]
      },
      {
        "text": "dime el despacho de alicia maria ageno pulido",
        "intent": "ask_teacher_desk",
        "entities": [
          {
            "start": 20,
            "end": 26,
            "value": "alicia",
            "entity": "teacher_name"
          },
          {
            "start": 27,
            "end": 45,
            "value": "maria ageno pulido",
            "entity": "teacher_surname"
          }
        ]
      },
      {
        "text": "cual es el despacho de jesus alonso alonso",
        "intent": "ask_teacher_desk",
        "entities": [
          {
            "start": 23,
            "end": 28,
            "value": "jesus",
            "entity": "teacher_name"
          },
          {
            "start": 29,
            "end": 42,
            "value": "alonso alonso",
            "entity": "teacher_surname"
          }
        ]
      },
      {
        "text": "despacho de jesus alonso alonso",
        "intent": "ask_teacher_desk",
        "entities": [
          {
            "start": 12,
            "end": 17,
            "value": "jesus",
            "entity": "teacher_name"
          },
          {
            "start": 18,
            "end": 31,
            "value": "alonso alonso",
            "entity": "teacher_surname"
          }
        ]
      },
      {
        "text": "dime el despacho de jesus alonso alonso",
        "intent": "ask_teacher_desk",
        "entities": [
          {
            "start": 20,
            "end": 25,
            "value": "jesus",
            "entity": "teacher_name"
          },
          {
            "start": 26,
            "end": 39,
            "value": "alonso alonso",
            "entity": "teacher_surname"
          }
        ]
      },
      {
        "text": "cual es el despacho de marcus aloysius bezem",
        "intent": "ask_teacher_desk",
        "entities": [
          {
            "start": 23,
            "end": 29,
            "value": "marcus",
            "entity": "teacher_name"
          },
          {
            "start": 30,
            "end": 44,
            "value": "aloysius bezem",
            "entity": "teacher_surname"
          }
        ]
      },
      {
        "text": "despacho de marcus aloysius bezem",
        "intent": "ask_teacher_desk",
        "entities": [
          {
            "start": 12,
            "end": 18,
            "value": "marcus",
            "entity": "teacher_name"
          },
          {
            "start": 19,
            "end": 33,
            "value": "aloysius bezem",
            "entity": "teacher_surname"
          }
        ]
      },
      {
        "text": "dime el despacho de marcus aloysius bezem",
        "intent": "ask_teacher_desk",
        "entities": [
          {
            "start": 20,
            "end": 26,
            "value": "marcus",
            "entity": "teacher_name"
          },
          {
            "start": 27,
            "end": 41,
            "value": "aloysius bezem",
            "entity": "teacher_surname"
          }
        ]
      },
      {
        "text": "cual es el despacho de ren\u00c3\u00a9 alquezar mancho",
        "intent": "ask_teacher_desk",
        "entities": [
          {
            "start": 23,
            "end": 28,
            "value": "ren\u00c3\u00a9",
            "entity": "teacher_name"
          },
          {
            "start": 29,
            "end": 44,
            "value": "alquezar mancho",
            "entity": "teacher_surname"
          }
        ]
      },
      {
        "text": "despacho de ren\u00c3\u00a9 alquezar mancho",
        "intent": "ask_teacher_desk",
        "entities": [
          {
            "start": 12,
            "end": 17,
            "value": "ren\u00c3\u00a9",
            "entity": "teacher_name"
          },
          {
            "start": 18,
            "end": 33,
            "value": "alquezar mancho",
            "entity": "teacher_surname"
          }
        ]
      },
      {
        "text": "dime el despacho de ren\u00c3\u00a9 alquezar mancho",
        "intent": "ask_teacher_desk",
        "entities": [
          {
            "start": 20,
            "end": 25,
            "value": "ren\u00c3\u00a9",
            "entity": "teacher_name"
          },
          {
            "start": 26,
            "end": 41,
            "value": "alquezar mancho",
            "entity": "teacher_surname"
          }
        ]
      },
      {
        "text": "cual es el despacho de maria del carme alvarez faura",
        "intent": "ask_teacher_desk",
        "entities": [
          {
            "start": 23,
            "end": 28,
            "value": "maria",
            "entity": "teacher_name"
          },
          {
            "start": 29,
            "end": 52,
            "value": "del carme alvarez faura",
            "entity": "teacher_surname"
          }
        ]
      },
      {
        "text": "despacho de maria del carme alvarez faura",
        "intent": "ask_teacher_desk",
        "entities": [
          {
            "start": 12,
            "end": 17,
            "value": "maria",
            "entity": "teacher_name"
          },
          {
            "start": 18,
            "end": 41,
            "value": "del carme alvarez faura",
            "entity": "teacher_surname"
          }
        ]
      },
      {
        "text": "dime el despacho de maria del carme alvarez faura",
        "intent": "ask_teacher_desk",
        "entities": [
          {
            "start": 20,
            "end": 25,
            "value": "maria",
            "entity": "teacher_name"
          },
          {
            "start": 26,
            "end": 49,
            "value": "del carme alvarez faura",
            "entity": "teacher_surname"
          }
        ]
      },
      {
        "text": "cual es el despacho de carlos andujar gran",
        "intent": "ask_teacher_desk",
        "entities": [
          {
            "start": 23,
            "end": 29,
            "value": "carlos",
            "entity": "teacher_name"
          },
          {
            "start": 30,
            "end": 42,
            "value": "andujar gran",
            "entity": "teacher_surname"
          }
        ]
      },
      {
        "text": "despacho de carlos andujar gran",
        "intent": "ask_teacher_desk",
        "entities": [
          {
            "start": 12,
            "end": 18,
            "value": "carlos",
            "entity": "teacher_name"
          },
          {
            "start": 19,
            "end": 31,
            "value": "andujar gran",
            "entity": "teacher_surname"
          }
        ]
      },
      {
        "text": "dime el despacho de carlos andujar gran",
        "intent": "ask_teacher_desk",
        "entities": [
          {
            "start": 20,
            "end": 26,
            "value": "carlos",
            "entity": "teacher_name"
          },
          {
            "start": 27,
            "end": 39,
            "value": "andujar gran",
            "entity": "teacher_surname"
          }
        ]
      },
      {
        "text": "cual es el despacho de oscar argudo medrano",
        "intent": "ask_teacher_desk",
        "entities": [
          {
            "start": 23,
            "end": 28,
            "value": "oscar",
            "entity": "teacher_name"
          },
          {
            "start": 29,
            "end": 43,
            "value": "argudo medrano",
            "entity": "teacher_surname"
          }
        ]
      },
      {
        "text": "despacho de oscar argudo medrano",
        "intent": "ask_teacher_desk",
        "entities": [
          {
            "start": 12,
            "end": 17,
            "value": "oscar",
            "entity": "teacher_name"
          },
          {
            "start": 18,
            "end": 32,
            "value": "argudo medrano",
            "entity": "teacher_surname"
          }
        ]
      },
      {
        "text": "dime el despacho de oscar argudo medrano",
        "intent": "ask_teacher_desk",
        "entities": [
          {
            "start": 20,
            "end": 25,
            "value": "oscar",
            "entity": "teacher_name"
          },
          {
            "start": 26,
            "end": 40,
            "value": "argudo medrano",
            "entity": "teacher_surname"
          }
        ]
      },
      {
        "text": "cual es el despacho de marta arias vicente",
        "intent": "ask_teacher_desk",
        "entities": [
          {
            "start": 23,
            "end": 28,
            "value": "marta",
            "entity": "teacher_name"
          },
          {
            "start": 29,
            "end": 42,
            "value": "arias vicente",
            "entity": "teacher_surname"
          }
        ]
      },
      {
        "text": "despacho de marta arias vicente",
        "intent": "ask_teacher_desk",
        "entities": [
          {
            "start": 12,
            "end": 17,
            "value": "marta",
            "entity": "teacher_name"
          },
          {
            "start": 18,
            "end": 31,
            "value": "arias vicente",
            "entity": "teacher_surname"
          }
        ]
      },
      {
        "text": "dime el despacho de marta arias vicente",
        "intent": "ask_teacher_desk",
        "entities": [
          {
            "start": 20,
            "end": 25,
            "value": "marta",
            "entity": "teacher_name"
          },
          {
            "start": 26,
            "end": 39,
            "value": "arias vicente",
            "entity": "teacher_surname"
          }
        ]
      },
      {
        "text": "cual es el despacho de argimiro arratia quesada",
        "intent": "ask_teacher_desk",
        "entities": [
          {
            "start": 23,
            "end": 31,
            "value": "argimiro",
            "entity": "teacher_name"
          },
          {
            "start": 32,
            "end": 47,
            "value": "arratia quesada",
            "entity": "teacher_surname"
          }
        ]
      },
      {
        "text": "despacho de argimiro arratia quesada",
        "intent": "ask_teacher_desk",
        "entities": [
          {
            "start": 12,
            "end": 20,
            "value": "argimiro",
            "entity": "teacher_name"
          },
          {
            "start": 21,
            "end": 36,
            "value": "arratia quesada",
            "entity": "teacher_surname"
          }
        ]
      },
      {
        "text": "dime el despacho de argimiro arratia quesada",
        "intent": "ask_teacher_desk",
        "entities": [
          {
            "start": 20,
            "end": 28,
            "value": "argimiro",
            "entity": "teacher_name"
          },
          {
            "start": 29,
            "end": 44,
            "value": "arratia quesada",
            "entity": "teacher_surname"
          }
        ]
      },
      {
        "text": "cual es el despacho de albert atserias peri",
        "intent": "ask_teacher_desk",
        "entities": [
          {
            "start": 23,
            "end": 29,
            "value": "albert",
            "entity": "teacher_name"
          },
          {
            "start": 30,
            "end": 43,
            "value": "atserias peri",
            "entity": "teacher_surname"
          }
        ]
      },
      {
        "text": "despacho de albert atserias peri",
        "intent": "ask_teacher_desk",
        "entities": [
          {
            "start": 12,
            "end": 18,
            "value": "albert",
            "entity": "teacher_name"
          },
          {
            "start": 19,
            "end": 32,
            "value": "atserias peri",
            "entity": "teacher_surname"
          }
        ]
      },
      {
        "text": "dime el despacho de albert atserias peri",
        "intent": "ask_teacher_desk",
        "entities": [
          {
            "start": 20,
            "end": 26,
            "value": "albert",
            "entity": "teacher_name"
          },
          {
            "start": 27,
            "end": 40,
            "value": "atserias peri",
            "entity": "teacher_surname"
          }
        ]
      },
      {
        "text": "cual es el despacho de maria dolors ayala vallespi",
        "intent": "ask_teacher_desk",
        "entities": [
          {
            "start": 23,
            "end": 28,
            "value": "maria",
            "entity": "teacher_name"
          },
          {
            "start": 29,
            "end": 50,
            "value": "dolors ayala vallespi",
            "entity": "teacher_surname"
          }
        ]
      },
      {
        "text": "despacho de maria dolors ayala vallespi",
        "intent": "ask_teacher_desk",
        "entities": [
          {
            "start": 12,
            "end": 17,
            "value": "maria",
            "entity": "teacher_name"
          },
          {
            "start": 18,
            "end": 39,
            "value": "dolors ayala vallespi",
            "entity": "teacher_surname"
          }
        ]
      },
      {
        "text": "dime el despacho de maria dolors ayala vallespi",
        "intent": "ask_teacher_desk",
        "entities": [
          {
            "start": 20,
            "end": 25,
            "value": "maria",
            "entity": "teacher_name"
          },
          {
            "start": 26,
            "end": 47,
            "value": "dolors ayala vallespi",
            "entity": "teacher_surname"
          }
        ]
      },
      {
        "text": "cual es el despacho de jaume baixeries juvilla",
        "intent": "ask_teacher_desk",
        "entities": [
          {
            "start": 23,
            "end": 28,
            "value": "jaume",
            "entity": "teacher_name"
          },
          {
            "start": 29,
            "end": 46,
            "value": "baixeries juvilla",
            "entity": "teacher_surname"
          }
        ]
      },
      {
        "text": "despacho de jaume baixeries juvilla",
        "intent": "ask_teacher_desk",
        "entities": [
          {
            "start": 12,
            "end": 17,
            "value": "jaume",
            "entity": "teacher_name"
          },
          {
            "start": 18,
            "end": 35,
            "value": "baixeries juvilla",
            "entity": "teacher_surname"
          }
        ]
      },
      {
        "text": "dime el despacho de jaume baixeries juvilla",
        "intent": "ask_teacher_desk",
        "entities": [
          {
            "start": 20,
            "end": 25,
            "value": "jaume",
            "entity": "teacher_name"
          },
          {
            "start": 26,
            "end": 43,
            "value": "baixeries juvilla",
            "entity": "teacher_surname"
          }
        ]
      },
      {
        "text": "cual es el despacho de jose luis balcazar navarro",
        "intent": "ask_teacher_desk",
        "entities": [
          {
            "start": 23,
            "end": 27,
            "value": "jose",
            "entity": "teacher_name"
          },
          {
            "start": 28,
            "end": 49,
            "value": "luis balcazar navarro",
            "entity": "teacher_surname"
          }
        ]
      },
      {
        "text": "despacho de jose luis balcazar navarro",
        "intent": "ask_teacher_desk",
        "entities": [
          {
            "start": 12,
            "end": 16,
            "value": "jose",
            "entity": "teacher_name"
          },
          {
            "start": 17,
            "end": 38,
            "value": "luis balcazar navarro",
            "entity": "teacher_surname"
          }
        ]
      },
      {
        "text": "dime el despacho de jose luis balcazar navarro",
        "intent": "ask_teacher_desk",
        "entities": [
          {
            "start": 20,
            "end": 24,
            "value": "jose",
            "entity": "teacher_name"
          },
          {
            "start": 25,
            "end": 46,
            "value": "luis balcazar navarro",
            "entity": "teacher_surname"
          }
        ]
      },
      {
        "text": "cual es el despacho de cristian barrue subirana",
        "intent": "ask_teacher_desk",
        "entities": [
          {
            "start": 23,
            "end": 31,
            "value": "cristian",
            "entity": "teacher_name"
          },
          {
            "start": 32,
            "end": 47,
            "value": "barrue subirana",
            "entity": "teacher_surname"
          }
        ]
      },
      {
        "text": "despacho de cristian barrue subirana",
        "intent": "ask_teacher_desk",
        "entities": [
          {
            "start": 12,
            "end": 20,
            "value": "cristian",
            "entity": "teacher_name"
          },
          {
            "start": 21,
            "end": 36,
            "value": "barrue subirana",
            "entity": "teacher_surname"
          }
        ]
      },
      {
        "text": "dime el despacho de cristian barrue subirana",
        "intent": "ask_teacher_desk",
        "entities": [
          {
            "start": 20,
            "end": 28,
            "value": "cristian",
            "entity": "teacher_name"
          },
          {
            "start": 29,
            "end": 44,
            "value": "barrue subirana",
            "entity": "teacher_surname"
          }
        ]
      },
      {
        "text": "cual es el despacho de javier bejar alonso",
        "intent": "ask_teacher_desk",
        "entities": [
          {
            "start": 23,
            "end": 29,
            "value": "javier",
            "entity": "teacher_name"
          },
          {
            "start": 30,
            "end": 42,
            "value": "bejar alonso",
            "entity": "teacher_surname"
          }
        ]
      },
      {
        "text": "despacho de javier bejar alonso",
        "intent": "ask_teacher_desk",
        "entities": [
          {
            "start": 12,
            "end": 18,
            "value": "javier",
            "entity": "teacher_name"
          },
          {
            "start": 19,
            "end": 31,
            "value": "bejar alonso",
            "entity": "teacher_surname"
          }
        ]
      },
      {
        "text": "dime el despacho de javier bejar alonso",
        "intent": "ask_teacher_desk",
        "entities": [
          {
            "start": 20,
            "end": 26,
            "value": "javier",
            "entity": "teacher_name"
          },
          {
            "start": 27,
            "end": 39,
            "value": "bejar alonso",
            "entity": "teacher_surname"
          }
        ]
      },
      {
        "text": "cual es el despacho de luis antonio belanche mu\u00c3\u00b1oz",
        "intent": "ask_teacher_desk",
        "entities": [
          {
            "start": 23,
            "end": 27,
            "value": "luis",
            "entity": "teacher_name"
          },
          {
            "start": 28,
            "end": 51,
            "value": "antonio belanche mu\u00c3\u00b1oz",
            "entity": "teacher_surname"
          }
        ]
      },
      {
        "text": "despacho de luis antonio belanche mu\u00c3\u00b1oz",
        "intent": "ask_teacher_desk",
        "entities": [
          {
            "start": 12,
            "end": 16,
            "value": "luis",
            "entity": "teacher_name"
          },
          {
            "start": 17,
            "end": 40,
            "value": "antonio belanche mu\u00c3\u00b1oz",
            "entity": "teacher_surname"
          }
        ]
      },
      {
        "text": "dime el despacho de luis antonio belanche mu\u00c3\u00b1oz",
        "intent": "ask_teacher_desk",
        "entities": [
          {
            "start": 20,
            "end": 24,
            "value": "luis",
            "entity": "teacher_name"
          },
          {
            "start": 25,
            "end": 48,
            "value": "antonio belanche mu\u00c3\u00b1oz",
            "entity": "teacher_surname"
          }
        ]
      },
      {
        "text": "cual es el despacho de maria josep blesa aguilera",
        "intent": "ask_teacher_desk",
        "entities": [
          {
            "start": 23,
            "end": 28,
            "value": "maria",
            "entity": "teacher_name"
          },
          {
            "start": 29,
            "end": 49,
            "value": "josep blesa aguilera",
            "entity": "teacher_surname"
          }
        ]
      },
      {
        "text": "despacho de maria josep blesa aguilera",
        "intent": "ask_teacher_desk",
        "entities": [
          {
            "start": 12,
            "end": 17,
            "value": "maria",
            "entity": "teacher_name"
          },
          {
            "start": 18,
            "end": 38,
            "value": "josep blesa aguilera",
            "entity": "teacher_surname"
          }
        ]
      },
      {
        "text": "dime el despacho de maria josep blesa aguilera",
        "intent": "ask_teacher_desk",
        "entities": [
          {
            "start": 20,
            "end": 25,
            "value": "maria",
            "entity": "teacher_name"
          },
          {
            "start": 26,
            "end": 46,
            "value": "josep blesa aguilera",
            "entity": "teacher_surname"
          }
        ]
      },
      {
        "text": "cual es el despacho de blum blum",
        "intent": "ask_teacher_desk",
        "entities": [
          {
            "start": 23,
            "end": 27,
            "value": "blum",
            "entity": "teacher_name"
          },
          {
            "start": 28,
            "end": 32,
            "value": "blum",
            "entity": "teacher_surname"
          }
        ]
      },
      {
        "text": "despacho de blum blum",
        "intent": "ask_teacher_desk",
        "entities": [
          {
            "start": 12,
            "end": 16,
            "value": "blum",
            "entity": "teacher_name"
          },
          {
            "start": 17,
            "end": 21,
            "value": "blum",
            "entity": "teacher_surname"
          }
        ]
      },
      {
        "text": "dime el despacho de blum blum",
        "intent": "ask_teacher_desk",
        "entities": [
          {
            "start": 20,
            "end": 24,
            "value": "blum",
            "entity": "teacher_name"
          },
          {
            "start": 25,
            "end": 29,
            "value": "blum",
            "entity": "teacher_surname"
          }
        ]
      },
      {
        "text": "cual es el despacho de ilario bonacina",
        "intent": "ask_teacher_desk",
        "entities": [
          {
            "start": 23,
            "end": 29,
            "value": "ilario",
            "entity": "teacher_name"
          },
          {
            "start": 30,
            "end": 38,
            "value": "bonacina",
            "entity": "teacher_surname"
          }
        ]
      },
      {
        "text": "despacho de ilario bonacina",
        "intent": "ask_teacher_desk",
        "entities": [
          {
            "start": 12,
            "end": 18,
            "value": "ilario",
            "entity": "teacher_name"
          },
          {
            "start": 19,
            "end": 27,
            "value": "bonacina",
            "entity": "teacher_surname"
          }
        ]
      },
      {
        "text": "dime el despacho de ilario bonacina",
        "intent": "ask_teacher_desk",
        "entities": [
          {
            "start": 20,
            "end": 26,
            "value": "ilario",
            "entity": "teacher_name"
          },
          {
            "start": 27,
            "end": 35,
            "value": "bonacina",
            "entity": "teacher_surname"
          }
        ]
      },
      {
        "text": "plazas libres de APA",
        "intent": "ask_free_spots",
        "entities": [
          {
            "start": 17,
            "end": 20,
            "value": "APA",
            "entity": "subject_acronym"
          }
        ]
      },
      {
        "text": "cuantas plazas quedan de APA",
        "intent": "ask_free_spots",
        "entities": [
          {
            "start": 25,
            "end": 28,
            "value": "APA",
            "entity": "subject_acronym"
          }
        ]
      },
      {
        "text": "plazas de APA",
        "intent": "ask_free_spots",
        "entities": [
          {
            "start": 10,
            "end": 13,
            "value": "APA",
            "entity": "subject_acronym"
          }
        ]
      },
      {
        "text": "plazas libres de APC",
        "intent": "ask_free_spots",
        "entities": [
          {
            "start": 17,
            "end": 20,
            "value": "APC",
            "entity": "subject_acronym"
          }
        ]
      },
      {
        "text": "cuantas plazas quedan de APC",
        "intent": "ask_free_spots",
        "entities": [
          {
            "start": 25,
            "end": 28,
            "value": "APC",
            "entity": "subject_acronym"
          }
        ]
      },
      {
        "text": "plazas de APC",
        "intent": "ask_free_spots",
        "entities": [
          {
            "start": 10,
            "end": 13,
            "value": "APC",
            "entity": "subject_acronym"
          }
        ]
      },
      {
        "text": "plazas libres de PAE",
        "intent": "ask_free_spots",
        "entities": [
          {
            "start": 17,
            "end": 20,
            "value": "PAE",
            "entity": "subject_acronym"
          }
        ]
      },
      {
        "text": "cuantas plazas quedan de PAE",
        "intent": "ask_free_spots",
        "entities": [
          {
            "start": 25,
            "end": 28,
            "value": "PAE",
            "entity": "subject_acronym"
          }
        ]
      },
      {
        "text": "plazas de PAE",
        "intent": "ask_free_spots",
        "entities": [
          {
            "start": 10,
            "end": 13,
            "value": "PAE",
            "entity": "subject_acronym"
          }
        ]
      },
      {
        "text": "plazas libres de MD",
        "intent": "ask_free_spots",
        "entities": [
          {
            "start": 17,
            "end": 19,
            "value": "MD",
            "entity": "subject_acronym"
          }
        ]
      },
      {
        "text": "cuantas plazas quedan de MD",
        "intent": "ask_free_spots",
        "entities": [
          {
            "start": 25,
            "end": 27,
            "value": "MD",
            "entity": "subject_acronym"
          }
        ]
      },
      {
        "text": "plazas de MD",
        "intent": "ask_free_spots",
        "entities": [
          {
            "start": 10,
            "end": 12,
            "value": "MD",
            "entity": "subject_acronym"
          }
        ]
      },
      {
        "text": "plazas libres de CAIM",
        "intent": "ask_free_spots",
        "entities": [
          {
            "start": 17,
            "end": 21,
            "value": "CAIM",
            "entity": "subject_acronym"
          }
        ]
      },
      {
        "text": "cuantas plazas quedan de CAIM",
        "intent": "ask_free_spots",
        "entities": [
          {
            "start": 25,
            "end": 29,
            "value": "CAIM",
            "entity": "subject_acronym"
          }
        ]
      },
      {
        "text": "plazas de CAIM",
        "intent": "ask_free_spots",
        "entities": [
          {
            "start": 10,
            "end": 14,
            "value": "CAIM",
            "entity": "subject_acronym"
          }
        ]
      },
      {
        "text": "plazas libres de IA",
        "intent": "ask_free_spots",
        "entities": [
          {
            "start": 17,
            "end": 19,
            "value": "IA",
            "entity": "subject_acronym"
          }
        ]
      },
      {
        "text": "cuantas plazas quedan de IA",
        "intent": "ask_free_spots",
        "entities": [
          {
            "start": 25,
            "end": 27,
            "value": "IA",
            "entity": "subject_acronym"
          }
        ]
      },
      {
        "text": "plazas de IA",
        "intent": "ask_free_spots",
        "entities": [
          {
            "start": 10,
            "end": 12,
            "value": "IA",
            "entity": "subject_acronym"
          }
        ]
      },
      {
        "text": "plazas libres de TC",
        "intent": "ask_free_spots",
        "entities": [
          {
            "start": 17,
            "end": 19,
            "value": "TC",
            "entity": "subject_acronym"
          }
        ]
      },
      {
        "text": "cuantas plazas quedan de TC",
        "intent": "ask_free_spots",
        "entities": [
          {
            "start": 25,
            "end": 27,
            "value": "TC",
            "entity": "subject_acronym"
          }
        ]
      },
      {
        "text": "plazas de TC",
        "intent": "ask_free_spots",
        "entities": [
          {
            "start": 10,
            "end": 12,
            "value": "TC",
            "entity": "subject_acronym"
          }
        ]
      },
      {
        "text": "plazas libres de FDM",
        "intent": "ask_free_spots",
        "entities": [
          {
            "start": 17,
            "end": 20,
            "value": "FDM",
            "entity": "subject_acronym"
          }
        ]
      },
      {
        "text": "cuantas plazas quedan de FDM",
        "intent": "ask_free_spots",
        "entities": [
          {
            "start": 25,
            "end": 28,
            "value": "FDM",
            "entity": "subject_acronym"
          }
        ]
      },
      {
        "text": "plazas de FDM",
        "intent": "ask_free_spots",
        "entities": [
          {
            "start": 10,
            "end": 13,
            "value": "FDM",
            "entity": "subject_acronym"
          }
        ]
      },
      {
        "text": "plazas libres de SIM",
        "intent": "ask_free_spots",
        "entities": [
          {
            "start": 17,
            "end": 20,
            "value": "SIM",
            "entity": "subject_acronym"
          }
        ]
      },
      {
        "text": "cuantas plazas quedan de SIM",
        "intent": "ask_free_spots",
        "entities": [
          {
            "start": 25,
            "end": 28,
            "value": "SIM",
            "entity": "subject_acronym"
          }
        ]
      },
      {
        "text": "plazas de SIM",
        "intent": "ask_free_spots",
        "entities": [
          {
            "start": 10,
            "end": 13,
            "value": "SIM",
            "entity": "subject_acronym"
          }
        ]
      },
      {
        "text": "plazas libres de M1",
        "intent": "ask_free_spots",
        "entities": [
          {
            "start": 17,
            "end": 19,
            "value": "M1",
            "entity": "subject_acronym"
          }
        ]
      },
      {
        "text": "cuantas plazas quedan de M1",
        "intent": "ask_free_spots",
        "entities": [
          {
            "start": 25,
            "end": 27,
            "value": "M1",
            "entity": "subject_acronym"
          }
        ]
      },
      {
        "text": "plazas de M1",
        "intent": "ask_free_spots",
        "entities": [
          {
            "start": 10,
            "end": 12,
            "value": "M1",
            "entity": "subject_acronym"
          }
        ]
      },
      {
        "text": "plazas libres de PROP",
        "intent": "ask_free_spots",
        "entities": [
          {
            "start": 17,
            "end": 21,
            "value": "PROP",
            "entity": "subject_acronym"
          }
        ]
      },
      {
        "text": "cuantas plazas quedan de PROP",
        "intent": "ask_free_spots",
        "entities": [
          {
            "start": 25,
            "end": 29,
            "value": "PROP",
            "entity": "subject_acronym"
          }
        ]
      },
      {
        "text": "plazas de PROP",
        "intent": "ask_free_spots",
        "entities": [
          {
            "start": 10,
            "end": 14,
            "value": "PROP",
            "entity": "subject_acronym"
          }
        ]
      },
      {
        "text": "plazas libres de PRO1",
        "intent": "ask_free_spots",
        "entities": [
          {
            "start": 17,
            "end": 21,
            "value": "PRO1",
            "entity": "subject_acronym"
          }
        ]
      },
      {
        "text": "cuantas plazas quedan de PRO1",
        "intent": "ask_free_spots",
        "entities": [
          {
            "start": 25,
            "end": 29,
            "value": "PRO1",
            "entity": "subject_acronym"
          }
        ]
      },
      {
        "text": "plazas de PRO1",
        "intent": "ask_free_spots",
        "entities": [
          {
            "start": 10,
            "end": 14,
            "value": "PRO1",
            "entity": "subject_acronym"
          }
        ]
      },
      {
        "text": "plazas libres de PRO2",
        "intent": "ask_free_spots",
        "entities": [
          {
            "start": 17,
            "end": 21,
            "value": "PRO2",
            "entity": "subject_acronym"
          }
        ]
      },
      {
        "text": "cuantas plazas quedan de PRO2",
        "intent": "ask_free_spots",
        "entities": [
          {
            "start": 25,
            "end": 29,
            "value": "PRO2",
            "entity": "subject_acronym"
          }
        ]
      },
      {
        "text": "plazas de PRO2",
        "intent": "ask_free_spots",
        "entities": [
          {
            "start": 10,
            "end": 14,
            "value": "PRO2",
            "entity": "subject_acronym"
          }
        ]
      },
      {
        "text": "horario de APA",
        "intent": "ask_subject_schedule",
        "entities": [
          {
            "start": 11,
            "end": 14,
            "value": "APA",
            "entity": "subject_acronym"
          }
        ]
      },
      {
        "text": "cual es el horario de APA",
        "intent": "ask_subject_schedule",
        "entities": [
          {
            "start": 22,
            "end": 25,
            "value": "APA",
            "entity": "subject_acronym"
          }
        ]
      },
      {
        "text": "a que hora tengo APA",
        "intent": "ask_subject_schedule",
        "entities": [
          {
            "start": 17,
            "end": 20,
            "value": "APA",
            "entity": "subject_acronym"
          }
        ]
      },
      {
        "text": "horario de APC",
        "intent": "ask_subject_schedule",
        "entities": [
          {
            "start": 11,
            "end": 14,
            "value": "APC",
            "entity": "subject_acronym"
          }
        ]
      },
      {
        "text": "cual es el horario de APC",
        "intent": "ask_subject_schedule",
        "entities": [
          {
            "start": 22,
            "end": 25,
            "value": "APC",
            "entity": "subject_acronym"
          }
        ]
      },
      {
        "text": "a que hora tengo APC",
        "intent": "ask_subject_schedule",
        "entities": [
          {
            "start": 17,
            "end": 20,
            "value": "APC",
            "entity": "subject_acronym"
          }
        ]
      },
      {
        "text": "horario de PAE",
        "intent": "ask_subject_schedule",
        "entities": [
          {
            "start": 11,
            "end": 14,
            "value": "PAE",
            "entity": "subject_acronym"
          }
        ]
      },
      {
        "text": "cual es el horario de PAE",
        "intent": "ask_subject_schedule",
        "entities": [
          {
            "start": 22,
            "end": 25,
            "value": "PAE",
            "entity": "subject_acronym"
          }
        ]
      },
      {
        "text": "a que hora tengo PAE",
        "intent": "ask_subject_schedule",
        "entities": [
          {
            "start": 17,
            "end": 20,
            "value": "PAE",
            "entity": "subject_acronym"
          }
        ]
      },
      {
        "text": "horario de MD",
        "intent": "ask_subject_schedule",
        "entities": [
          {
            "start": 11,
            "end": 13,
            "value": "MD",
            "entity": "subject_acronym"
          }
        ]
      },
      {
        "text": "cual es el horario de MD",
        "intent": "ask_subject_schedule",
        "entities": [
          {
            "start": 22,
            "end": 24,
            "value": "MD",
            "entity": "subject_acronym"
          }
        ]
      },
      {
        "text": "a que hora tengo MD",
        "intent": "ask_subject_schedule",
        "entities": [
          {
            "start": 17,
            "end": 19,
            "value": "MD",
            "entity": "subject_acronym"
          }
        ]
      },
      {
        "text": "horario de CAIM",
        "intent": "ask_subject_schedule",
        "entities": [
          {
            "start": 11,
            "end": 15,
            "value": "CAIM",
            "entity": "subject_acronym"
          }
        ]
      },
      {
        "text": "cual es el horario de CAIM",
        "intent": "ask_subject_schedule",
        "entities": [
          {
            "start": 22,
            "end": 26,
            "value": "CAIM",
            "entity": "subject_acronym"
          }
        ]
      },
      {
        "text": "a que hora tengo CAIM",
        "intent": "ask_subject_schedule",
        "entities": [
          {
            "start": 17,
            "end": 21,
            "value": "CAIM",
            "entity": "subject_acronym"
          }
        ]
      },
      {
        "text": "horario de IA",
        "intent": "ask_subject_schedule",
        "entities": [
          {
            "start": 11,
            "end": 13,
            "value": "IA",
            "entity": "subject_acronym"
          }
        ]
      },
      {
        "text": "cual es el horario de IA",
        "intent": "ask_subject_schedule",
        "entities": [
          {
            "start": 22,
            "end": 24,
            "value": "IA",
            "entity": "subject_acronym"
          }
        ]
      },
      {
        "text": "a que hora tengo IA",
        "intent": "ask_subject_schedule",
        "entities": [
          {
            "start": 17,
            "end": 19,
            "value": "IA",
            "entity": "subject_acronym"
          }
        ]
      },
      {
        "text": "horario de TC",
        "intent": "ask_subject_schedule",
        "entities": [
          {
            "start": 11,
            "end": 13,
            "value": "TC",
            "entity": "subject_acronym"
          }
        ]
      },
      {
        "text": "cual es el horario de TC",
        "intent": "ask_subject_schedule",
        "entities": [
          {
            "start": 22,
            "end": 24,
            "value": "TC",
            "entity": "subject_acronym"
          }
        ]
      },
      {
        "text": "a que hora tengo TC",
        "intent": "ask_subject_schedule",
        "entities": [
          {
            "start": 17,
            "end": 19,
            "value": "TC",
            "entity": "subject_acronym"
          }
        ]
      },
      {
        "text": "horario de FDM",
        "intent": "ask_subject_schedule",
        "entities": [
          {
            "start": 11,
            "end": 14,
            "value": "FDM",
            "entity": "subject_acronym"
          }
        ]
      },
      {
        "text": "cual es el horario de FDM",
        "intent": "ask_subject_schedule",
        "entities": [
          {
            "start": 22,
            "end": 25,
            "value": "FDM",
            "entity": "subject_acronym"
          }
        ]
      },
      {
        "text": "a que hora tengo FDM",
        "intent": "ask_subject_schedule",
        "entities": [
          {
            "start": 17,
            "end": 20,
            "value": "FDM",
            "entity": "subject_acronym"
          }
        ]
      },
      {
        "text": "horario de SIM",
        "intent": "ask_subject_schedule",
        "entities": [
          {
            "start": 11,
            "end": 14,
            "value": "SIM",
            "entity": "subject_acronym"
          }
        ]
      },
      {
        "text": "cual es el horario de SIM",
        "intent": "ask_subject_schedule",
        "entities": [
          {
            "start": 22,
            "end": 25,
            "value": "SIM",
            "entity": "subject_acronym"
          }
        ]
      },
      {
        "text": "a que hora tengo SIM",
        "intent": "ask_subject_schedule",
        "entities": [
          {
            "start": 17,
            "end": 20,
            "value": "SIM",
            "entity": "subject_acronym"
          }
        ]
      },
      {
        "text": "horario de M1",
        "intent": "ask_subject_schedule",
        "entities": [
          {
            "start": 11,
            "end": 13,
            "value": "M1",
            "entity": "subject_acronym"
          }
        ]
      },
      {
        "text": "cual es el horario de M1",
        "intent": "ask_subject_schedule",
        "entities": [
          {
            "start": 22,
            "end": 24,
            "value": "M1",
            "entity": "subject_acronym"
          }
        ]
      },
      {
        "text": "a que hora tengo M1",
        "intent": "ask_subject_schedule",
        "entities": [
          {
            "start": 17,
            "end": 19,
            "value": "M1",
            "entity": "subject_acronym"
          }
        ]
      },
      {
        "text": "horario de PROP",
        "intent": "ask_subject_schedule",
        "entities": [
          {
            "start": 11,
            "end": 15,
            "value": "PROP",
            "entity": "subject_acronym"
          }
        ]
      },
      {
        "text": "cual es el horario de PROP",
        "intent": "ask_subject_schedule",
        "entities": [
          {
            "start": 22,
            "end": 26,
            "value": "PROP",
            "entity": "subject_acronym"
          }
        ]
      },
      {
        "text": "a que hora tengo PROP",
        "intent": "ask_subject_schedule",
        "entities": [
          {
            "start": 17,
            "end": 21,
            "value": "PROP",
            "entity": "subject_acronym"
          }
        ]
      },
      {
        "text": "horario de PRO1",
        "intent": "ask_subject_schedule",
        "entities": [
          {
            "start": 11,
            "end": 15,
            "value": "PRO1",
            "entity": "subject_acronym"
          }
        ]
      },
      {
        "text": "cual es el horario de PRO1",
        "intent": "ask_subject_schedule",
        "entities": [
          {
            "start": 22,
            "end": 26,
            "value": "PRO1",
            "entity": "subject_acronym"
          }
        ]
      },
      {
        "text": "a que hora tengo PRO1",
        "intent": "ask_subject_schedule",
        "entities": [
          {
            "start": 17,
            "end": 21,
            "value": "PRO1",
            "entity": "subject_acronym"
          }
        ]
      },
      {
        "text": "horario de PRO2",
        "intent": "ask_subject_schedule",
        "entities": [
          {
            "start": 11,
            "end": 15,
            "value": "PRO2",
            "entity": "subject_acronym"
          }
        ]
      },
      {
        "text": "cual es el horario de PRO2",
        "intent": "ask_subject_schedule",
        "entities": [
          {
            "start": 22,
            "end": 26,
            "value": "PRO2",
            "entity": "subject_acronym"
          }
        ]
      },
      {
        "text": "a que hora tengo PRO2",
        "intent": "ask_subject_schedule",
        "entities": [
          {
            "start": 17,
            "end": 21,
            "value": "PRO2",
            "entity": "subject_acronym"
          }
        ]
      },
      {
        "text": "en que clase hay APA",
        "intent": "ask_subject_classroom",
        "entities": [
          {
            "start": 17,
            "end": 20,
            "value": "APA",
            "entity": "subject_acronym"
          }
        ]
      },
      {
        "text": "en que clase tengo APA",
        "intent": "ask_subject_classroom",
        "entities": [
          {
            "start": 19,
            "end": 22,
            "value": "APA",
            "entity": "subject_acronym"
          }
        ]
      },
      {
        "text": "donde tengo APA",
        "intent": "ask_subject_classroom",
        "entities": [
          {
            "start": 12,
            "end": 15,
            "value": "APA",
            "entity": "subject_acronym"
          }
        ]
      },
      {
        "text": "en que clase hay APC",
        "intent": "ask_subject_classroom",
        "entities": [
          {
            "start": 17,
            "end": 20,
            "value": "APC",
            "entity": "subject_acronym"
          }
        ]
      },
      {
        "text": "en que clase tengo APC",
        "intent": "ask_subject_classroom",
        "entities": [
          {
            "start": 19,
            "end": 22,
            "value": "APC",
            "entity": "subject_acronym"
          }
        ]
      },
      {
        "text": "donde tengo APC",
        "intent": "ask_subject_classroom",
        "entities": [
          {
            "start": 12,
            "end": 15,
            "value": "APC",
            "entity": "subject_acronym"
          }
        ]
      },
      {
        "text": "en que clase hay PAE",
        "intent": "ask_subject_classroom",
        "entities": [
          {
            "start": 17,
            "end": 20,
            "value": "PAE",
            "entity": "subject_acronym"
          }
        ]
      },
      {
        "text": "en que clase tengo PAE",
        "intent": "ask_subject_classroom",
        "entities": [
          {
            "start": 19,
            "end": 22,
            "value": "PAE",
            "entity": "subject_acronym"
          }
        ]
      },
      {
        "text": "donde tengo PAE",
        "intent": "ask_subject_classroom",
        "entities": [
          {
            "start": 12,
            "end": 15,
            "value": "PAE",
            "entity": "subject_acronym"
          }
        ]
      },
      {
        "text": "en que clase hay MD",
        "intent": "ask_subject_classroom",
        "entities": [
          {
            "start": 17,
            "end": 19,
            "value": "MD",
            "entity": "subject_acronym"
          }
        ]
      },
      {
        "text": "en que clase tengo MD",
        "intent": "ask_subject_classroom",
        "entities": [
          {
            "start": 19,
            "end": 21,
            "value": "MD",
            "entity": "subject_acronym"
          }
        ]
      },
      {
        "text": "donde tengo MD",
        "intent": "ask_subject_classroom",
        "entities": [
          {
            "start": 12,
            "end": 14,
            "value": "MD",
            "entity": "subject_acronym"
          }
        ]
      },
      {
        "text": "en que clase hay CAIM",
        "intent": "ask_subject_classroom",
        "entities": [
          {
            "start": 17,
            "end": 21,
            "value": "CAIM",
            "entity": "subject_acronym"
          }
        ]
      },
      {
        "text": "en que clase tengo CAIM",
        "intent": "ask_subject_classroom",
        "entities": [
          {
            "start": 19,
            "end": 23,
            "value": "CAIM",
            "entity": "subject_acronym"
          }
        ]
      },
      {
        "text": "donde tengo CAIM",
        "intent": "ask_subject_classroom",
        "entities": [
          {
            "start": 12,
            "end": 16,
            "value": "CAIM",
            "entity": "subject_acronym"
          }
        ]
      },
      {
        "text": "en que clase hay IA",
        "intent": "ask_subject_classroom",
        "entities": [
          {
            "start": 17,
            "end": 19,
            "value": "IA",
            "entity": "subject_acronym"
          }
        ]
      },
      {
        "text": "en que clase tengo IA",
        "intent": "ask_subject_classroom",
        "entities": [
          {
            "start": 19,
            "end": 21,
            "value": "IA",
            "entity": "subject_acronym"
          }
        ]
      },
      {
        "text": "donde tengo IA",
        "intent": "ask_subject_classroom",
        "entities": [
          {
            "start": 12,
            "end": 14,
            "value": "IA",
            "entity": "subject_acronym"
          }
        ]
      },
      {
        "text": "en que clase hay TC",
        "intent": "ask_subject_classroom",
        "entities": [
          {
            "start": 17,
            "end": 19,
            "value": "TC",
            "entity": "subject_acronym"
          }
        ]
      },
      {
        "text": "en que clase tengo TC",
        "intent": "ask_subject_classroom",
        "entities": [
          {
            "start": 19,
            "end": 21,
            "value": "TC",
            "entity": "subject_acronym"
          }
        ]
      },
      {
        "text": "donde tengo TC",
        "intent": "ask_subject_classroom",
        "entities": [
          {
            "start": 12,
            "end": 14,
            "value": "TC",
            "entity": "subject_acronym"
          }
        ]
      },
      {
        "text": "en que clase hay FDM",
        "intent": "ask_subject_classroom",
        "entities": [
          {
            "start": 17,
            "end": 20,
            "value": "FDM",
            "entity": "subject_acronym"
          }
        ]
      },
      {
        "text": "en que clase tengo FDM",
        "intent": "ask_subject_classroom",
        "entities": [
          {
            "start": 19,
            "end": 22,
            "value": "FDM",
            "entity": "subject_acronym"
          }
        ]
      },
      {
        "text": "donde tengo FDM",
        "intent": "ask_subject_classroom",
        "entities": [
          {
            "start": 12,
            "end": 15,
            "value": "FDM",
            "entity": "subject_acronym"
          }
        ]
      },
      {
        "text": "en que clase hay SIM",
        "intent": "ask_subject_classroom",
        "entities": [
          {
            "start": 17,
            "end": 20,
            "value": "SIM",
            "entity": "subject_acronym"
          }
        ]
      },
      {
        "text": "en que clase tengo SIM",
        "intent": "ask_subject_classroom",
        "entities": [
          {
            "start": 19,
            "end": 22,
            "value": "SIM",
            "entity": "subject_acronym"
          }
        ]
      },
      {
        "text": "donde tengo SIM",
        "intent": "ask_subject_classroom",
        "entities": [
          {
            "start": 12,
            "end": 15,
            "value": "SIM",
            "entity": "subject_acronym"
          }
        ]
      },
      {
        "text": "en que clase hay M1",
        "intent": "ask_subject_classroom",
        "entities": [
          {
            "start": 17,
            "end": 19,
            "value": "M1",
            "entity": "subject_acronym"
          }
        ]
      },
      {
        "text": "en que clase tengo M1",
        "intent": "ask_subject_classroom",
        "entities": [
          {
            "start": 19,
            "end": 21,
            "value": "M1",
            "entity": "subject_acronym"
          }
        ]
      },
      {
        "text": "donde tengo M1",
        "intent": "ask_subject_classroom",
        "entities": [
          {
            "start": 12,
            "end": 14,
            "value": "M1",
            "entity": "subject_acronym"
          }
        ]
      },
      {
        "text": "en que clase hay PROP",
        "intent": "ask_subject_classroom",
        "entities": [
          {
            "start": 17,
            "end": 21,
            "value": "PROP",
            "entity": "subject_acronym"
          }
        ]
      },
      {
        "text": "en que clase tengo PROP",
        "intent": "ask_subject_classroom",
        "entities": [
          {
            "start": 19,
            "end": 23,
            "value": "PROP",
            "entity": "subject_acronym"
          }
        ]
      },
      {
        "text": "donde tengo PROP",
        "intent": "ask_subject_classroom",
        "entities": [
          {
            "start": 12,
            "end": 16,
            "value": "PROP",
            "entity": "subject_acronym"
          }
        ]
      },
      {
        "text": "en que clase hay PRO1",
        "intent": "ask_subject_classroom",
        "entities": [
          {
            "start": 17,
            "end": 21,
            "value": "PRO1",
            "entity": "subject_acronym"
          }
        ]
      },
      {
        "text": "en que clase tengo PRO1",
        "intent": "ask_subject_classroom",
        "entities": [
          {
            "start": 19,
            "end": 23,
            "value": "PRO1",
            "entity": "subject_acronym"
          }
        ]
      },
      {
        "text": "donde tengo PRO1",
        "intent": "ask_subject_classroom",
        "entities": [
          {
            "start": 12,
            "end": 16,
            "value": "PRO1",
            "entity": "subject_acronym"
          }
        ]
      },
      {
        "text": "en que clase hay PRO2",
        "intent": "ask_subject_classroom",
        "entities": [
          {
            "start": 17,
            "end": 21,
            "value": "PRO2",
            "entity": "subject_acronym"
          }
        ]
      },
      {
        "text": "en que clase tengo PRO2",
        "intent": "ask_subject_classroom",
        "entities": [
          {
            "start": 19,
            "end": 23,
            "value": "PRO2",
            "entity": "subject_acronym"
          }
        ]
      },
      {
        "text": "donde tengo PRO2",
        "intent": "ask_subject_classroom",
        "entities": [
          {
            "start": 12,
            "end": 16,
            "value": "PRO2",
            "entity": "subject_acronym"
          }
        ]
      },
      {
        "text": "cual es el horario de APA",
        "intent": "ask_subject_schedule",
        "entities": [
          {
            "start": 22,
            "end": 25,
            "value": "APA",
            "entity": "subject_acronym"
          }
        ]
      },
      {
        "text": "a que hora tengo APA",
        "intent": "ask_subject_schedule",
        "entities": [
          {
            "start": 17,
            "end": 20,
            "value": "APA",
            "entity": "subject_acronym"
          }
        ]
      },
      {
        "text": "horario de APA",
        "intent": "ask_subject_schedule",
        "entities": [
          {
            "start": 11,
            "end": 14,
            "value": "APA",
            "entity": "subject_acronym"
          }
        ]
      },
      {
        "text": "cual es el horario de APC",
        "intent": "ask_subject_schedule",
        "entities": [
          {
            "start": 22,
            "end": 25,
            "value": "APC",
            "entity": "subject_acronym"
          }
        ]
      },
      {
        "text": "a que hora tengo APC",
        "intent": "ask_subject_schedule",
        "entities": [
          {
            "start": 17,
            "end": 20,
            "value": "APC",
            "entity": "subject_acronym"
          }
        ]
      },
      {
        "text": "horario de APC",
        "intent": "ask_subject_schedule",
        "entities": [
          {
            "start": 11,
            "end": 14,
            "value": "APC",
            "entity": "subject_acronym"
          }
        ]
      },
      {
        "text": "cual es el horario de PAE",
        "intent": "ask_subject_schedule",
        "entities": [
          {
            "start": 22,
            "end": 25,
            "value": "PAE",
            "entity": "subject_acronym"
          }
        ]
      },
      {
        "text": "a que hora tengo PAE",
        "intent": "ask_subject_schedule",
        "entities": [
          {
            "start": 17,
            "end": 20,
            "value": "PAE",
            "entity": "subject_acronym"
          }
        ]
      },
      {
        "text": "horario de PAE",
        "intent": "ask_subject_schedule",
        "entities": [
          {
            "start": 11,
            "end": 14,
            "value": "PAE",
            "entity": "subject_acronym"
          }
        ]
      },
      {
        "text": "cual es el horario de MD",
        "intent": "ask_subject_schedule",
        "entities": [
          {
            "start": 22,
            "end": 24,
            "value": "MD",
            "entity": "subject_acronym"
          }
        ]
      },
      {
        "text": "a que hora tengo MD",
        "intent": "ask_subject_schedule",
        "entities": [
          {
            "start": 17,
            "end": 19,
            "value": "MD",
            "entity": "subject_acronym"
          }
        ]
      },
      {
        "text": "horario de MD",
        "intent": "ask_subject_schedule",
        "entities": [
          {
            "start": 11,
            "end": 13,
            "value": "MD",
            "entity": "subject_acronym"
          }
        ]
      },
      {
        "text": "cual es el horario de CAIM",
        "intent": "ask_subject_schedule",
        "entities": [
          {
            "start": 22,
            "end": 26,
            "value": "CAIM",
            "entity": "subject_acronym"
          }
        ]
      },
      {
        "text": "a que hora tengo CAIM",
        "intent": "ask_subject_schedule",
        "entities": [
          {
            "start": 17,
            "end": 21,
            "value": "CAIM",
            "entity": "subject_acronym"
          }
        ]
      },
      {
        "text": "horario de CAIM",
        "intent": "ask_subject_schedule",
        "entities": [
          {
            "start": 11,
            "end": 15,
            "value": "CAIM",
            "entity": "subject_acronym"
          }
        ]
      },
      {
        "text": "cual es el horario de IA",
        "intent": "ask_subject_schedule",
        "entities": [
          {
            "start": 22,
            "end": 24,
            "value": "IA",
            "entity": "subject_acronym"
          }
        ]
      },
      {
        "text": "a que hora tengo IA",
        "intent": "ask_subject_schedule",
        "entities": [
          {
            "start": 17,
            "end": 19,
            "value": "IA",
            "entity": "subject_acronym"
          }
        ]
      },
      {
        "text": "horario de IA",
        "intent": "ask_subject_schedule",
        "entities": [
          {
            "start": 11,
            "end": 13,
            "value": "IA",
            "entity": "subject_acronym"
          }
        ]
      },
      {
        "text": "cual es el horario de TC",
        "intent": "ask_subject_schedule",
        "entities": [
          {
            "start": 22,
            "end": 24,
            "value": "TC",
            "entity": "subject_acronym"
          }
        ]
      },
      {
        "text": "a que hora tengo TC",
        "intent": "ask_subject_schedule",
        "entities": [
          {
            "start": 17,
            "end": 19,
            "value": "TC",
            "entity": "subject_acronym"
          }
        ]
      },
      {
        "text": "horario de TC",
        "intent": "ask_subject_schedule",
        "entities": [
          {
            "start": 11,
            "end": 13,
            "value": "TC",
            "entity": "subject_acronym"
          }
        ]
      },
      {
        "text": "cual es el horario de FDM",
        "intent": "ask_subject_schedule",
        "entities": [
          {
            "start": 22,
            "end": 25,
            "value": "FDM",
            "entity": "subject_acronym"
          }
        ]
      },
      {
        "text": "a que hora tengo FDM",
        "intent": "ask_subject_schedule",
        "entities": [
          {
            "start": 17,
            "end": 20,
            "value": "FDM",
            "entity": "subject_acronym"
          }
        ]
      },
      {
        "text": "horario de FDM",
        "intent": "ask_subject_schedule",
        "entities": [
          {
            "start": 11,
            "end": 14,
            "value": "FDM",
            "entity": "subject_acronym"
          }
        ]
      },
      {
        "text": "cual es el horario de SIM",
        "intent": "ask_subject_schedule",
        "entities": [
          {
            "start": 22,
            "end": 25,
            "value": "SIM",
            "entity": "subject_acronym"
          }
        ]
      },
      {
        "text": "a que hora tengo SIM",
        "intent": "ask_subject_schedule",
        "entities": [
          {
            "start": 17,
            "end": 20,
            "value": "SIM",
            "entity": "subject_acronym"
          }
        ]
      },
      {
        "text": "horario de SIM",
        "intent": "ask_subject_schedule",
        "entities": [
          {
            "start": 11,
            "end": 14,
            "value": "SIM",
            "entity": "subject_acronym"
          }
        ]
      },
      {
        "text": "cual es el horario de M1",
        "intent": "ask_subject_schedule",
        "entities": [
          {
            "start": 22,
            "end": 24,
            "value": "M1",
            "entity": "subject_acronym"
          }
        ]
      },
      {
        "text": "a que hora tengo M1",
        "intent": "ask_subject_schedule",
        "entities": [
          {
            "start": 17,
            "end": 19,
            "value": "M1",
            "entity": "subject_acronym"
          }
        ]
      },
      {
        "text": "horario de M1",
        "intent": "ask_subject_schedule",
        "entities": [
          {
            "start": 11,
            "end": 13,
            "value": "M1",
            "entity": "subject_acronym"
          }
        ]
      },
      {
        "text": "cual es el horario de PROP",
        "intent": "ask_subject_schedule",
        "entities": [
          {
            "start": 22,
            "end": 26,
            "value": "PROP",
            "entity": "subject_acronym"
          }
        ]
      },
      {
        "text": "a que hora tengo PROP",
        "intent": "ask_subject_schedule",
        "entities": [
          {
            "start": 17,
            "end": 21,
            "value": "PROP",
            "entity": "subject_acronym"
          }
        ]
      },
      {
        "text": "horario de PROP",
        "intent": "ask_subject_schedule",
        "entities": [
          {
            "start": 11,
            "end": 15,
            "value": "PROP",
            "entity": "subject_acronym"
          }
        ]
      },
      {
        "text": "cual es el horario de PRO1",
        "intent": "ask_subject_schedule",
        "entities": [
          {
            "start": 22,
            "end": 26,
            "value": "PRO1",
            "entity": "subject_acronym"
          }
        ]
      },
      {
        "text": "a que hora tengo PRO1",
        "intent": "ask_subject_schedule",
        "entities": [
          {
            "start": 17,
            "end": 21,
            "value": "PRO1",
            "entity": "subject_acronym"
          }
        ]
      },
      {
        "text": "horario de PRO1",
        "intent": "ask_subject_schedule",
        "entities": [
          {
            "start": 11,
            "end": 15,
            "value": "PRO1",
            "entity": "subject_acronym"
          }
        ]
      },
      {
        "text": "cual es el horario de PRO2",
        "intent": "ask_subject_schedule",
        "entities": [
          {
            "start": 22,
            "end": 26,
            "value": "PRO2",
            "entity": "subject_acronym"
          }
        ]
      },
      {
        "text": "a que hora tengo PRO2",
        "intent": "ask_subject_schedule",
        "entities": [
          {
            "start": 17,
            "end": 21,
            "value": "PRO2",
            "entity": "subject_acronym"
          }
        ]
      },
      {
        "text": "horario de PRO2",
        "intent": "ask_subject_schedule",
        "entities": [
          {
            "start": 11,
            "end": 15,
            "value": "PRO2",
            "entity": "subject_acronym"
          }
        ]
      }
    ]
  }
}